Workbook
Name Cash_minimum: #REF!

Sheet Summary
A1: Summary Sheet | E1: Date | F1: =TODAY() -> 45861
D2: Job Selling Price | E2: =F52 -> 90915.735
A3: Builder | B3: Bird Dog Group | E3: Model
A4: Lot | E4: Elevation
A5: Subdivision
A6: Customer | B6: Ebert
A7: Address | B7: 2440 Beretania Circle
A8: City/St/Zip | B8: Charlotte, NC
F9: Rates/Hr
C10: Qty of Systems | D10: 4 | E10: Rough Install | F10: 26
C11: Total Ton | D11: =4+2+4+2 -> 12 | E11: Trim Install | F11: 28
E12: Technician | F12: 32
A13: Direct Cost | H13: Equipment "A"
A14: Labor | B14: Rough In | D14: ='Rough Labor'!F47 -> 5845 | F14: =D14 -> 5845 | H14: System 1 | I14: Model # | J14: Cost | K14: Main 1st Fl
B15: Finish/Trim | D15: ='Trim Labor'!F46 -> 1218 | F15: =D15 -> 1218 | H15: AHU/Furnace | I15: S9X2C100U5PSBB | J15: 1231 | K15: 4 Ton
B16: Gas Pipe | D16: ='Gas PIpe'!F38 -> 3515 | F16: =D16 -> 3515 | H16: Elec Htr/Evap Coil | I16: 5TXCC007AS3HCA | J16: 495 | K16: Gas | P16: 400
B17: Start Up | D17: 24 | E17: Job Incentive | F17: =D17*F12 -> 768 | H17: Heat Pump/AC | I17: 5TTR7048A1000A | J17: 2089
B18: Hourly | C18: 32 | D18: 24 | F18: =D18*F12 -> 768 | H18: ERV | I18: EERVR200A1P00B | J18: 904
B19: Delivery | D19: 375 | F19: =D19 -> 375 | H19: Thermostat
B20: Roof Cap | D20: 0 | F20: =D20 -> 0 | H20: Filter | I20: EFD210DLFR000A | J20: 815
B21: Job Incentive | D21: 0.05 | F21: =(F14+F15+F16+F17)*D21 -> 567.3 | H21: System 2 | I21: Model # | J21: Cost | K21: Master
B22: Warranty | D22: 0.05 | F22: =(SUM(F14:F21))*D22 -> 652.815 | H22: AHU/Furnace | I22: S9X2B060U4PSBB | J22: 1012 | K22: 2 Ton
E23: Total Labor Cost | F23: =SUM(F14:F22) -> 13709.115 | H23: Elec Htr/Evap Coil | I23: 5TXCB006AS3HCA | J23: 481 | K23: Gas
A24: Material | B24: Equipment | C24: "A" | D24: =J43 -> 15691 | F24: =D24 -> 15691 | H24: Heat Pump/AC | I24: 5TTR7024A1000A | J24: 1641
B25: Materials | C25: "B" | D25: =Materials!F999 -> 22497.01 | F25: =D25 -> 22497.01 | H25: ERV | I25: EERVR100A1P00B | J25: 727
B26: Supplies | C26: "C" | D26: 0.85% of B | F26: =0.085*F25 -> 1912.2459 | H26: Thermostat
B27: Inflation | D27: 2% A & 8% of B+C | F27: =F24*0.02+(F25+F26)*0.08 -> 2266.5605 | H27: Filter | I27: EFD175DLFR000A | J27: 762
B28: Warranty Materials | D28: 3.0% of A | F28: =0.02*F24 -> 313.82 | H28: System 3 | I28: Model # | J28: Cost | K28: 2nd Floor
E29: Total Material Cost | F29: =SUM(F24:F28) -> 42680.636 | H29: AHU/Furnace | I29: S9X2C100U5PSBB | J29: 1231 | K29: 4 Ton
A30: RIP | B30: Permit Cost | D30: 0 | F30: =D30 -> 0 | H30: Elec Htr/Evap Coil | I30: 5TXCC007AS3HCA | J30: 495
B31: Rentals | D31: 150 | F31: =D31 -> 150 | H31: Heat Pump/AC | I31: 5TTR7048A1000A | J31: 2089
B32: Backcharges | D32: 100 | F32: =D32 -> 100 | H32: ERV | I32: EERVR200A1P00B | J32: 904
B33: Freight | D33: 0.005 | F33: =D33*F29 -> 213.40318 | H33: Thermostat
E34: Total RIP Cost | F34: =SUM(F30:F33) -> 463.40318 | H34: Filter | I34: EFD210DLFR000A | J34: 815
E35: Total Direct Cost | F35: =F23+F29+F34 -> 56853.154 | H35: System 3 | I35: Model # | J35: Cost | K35: ADU Bldg
A36: Overhead | H36: AHU/Furnace | I36: S9X2B060U4PSBB | J36: 1012 | K36: 2 Ton
B37: Labor Overhead | D37: 0.1 | F37: =D37*F35 -> 5685.3154 | G37: Direct | H37: Elec Htr/Evap Coil | I37: 5TXCB006AS3HCA | J37: 481
B38: Direct Overhead | D38: 0.06 | F38: =D38*F35 -> 3411.1893 | G38: Direct | H38: Heat Pump/AC | I38: 5TTR7024A1000A | J38: 1641
B39: Admin | D39: 0.015 | F39: =D39*F35 -> 852.79732 | G39: Direct | H39: ERV | I39: EERVR100A1P00B | J39: 727
B40: Insurance | D40: 0.035 | F40: =D40*F35 -> 1989.8604 | G40: Direct | H40: Thermostat
B41: TTBE | D41: 0.0775 | F41: =D41*F35 -> 4406.1195 | G41: Direct | H41: Filter | I41: EFD175DLFR000A | J41: 762
B42: Warehouse | D42: 0.0205 | F42: =D42*F35 -> 1165.4897 | G42: Direct
B43: Supervision | D43: 0.105 | F43: =D43*F23 -> 1439.4571 | G43: Labor | J43: =SUM(J15:J34) -> 15691
B44: Tools | D44: 0.005 | F44: =D44*F23 -> 68.545575 | G44: Labor
B45: Truck | D45: 0.115 | F45: =D45*F23 -> 1576.5482 | G45: Labor | H45: Labor Margin | J45: =F23/F52 -> 0.15078925
E46: Total Overhead Cost | F46: =SUM(F37:F45) -> 20595.322 | H46: Material Margin | J46: =F29/F52 -> 0.46945269
A47: Profit & Tax | H47: R.I.P Margin | J47: =F34/F52 -> 0.0050970625
B48: Profit Percentage | D48: 0.1 | F48: =D48*(F35+F46) -> 7744.8477 | H48: Gross Margin | J48: =1-F35/F52 -> 0.374661
B49: Diff Factor | D49: 5 | F49: =IF(D49=1,(0.01*(F37+F46)),IF(D49=2,(0.025*(F37+F46)),IF(D49=3,(0.05*(F37+F46)),IF(D49=4,(0.075*(F37+F46)),IF(D49=5,(0.1*(F37+F46)),0))))) -> 2628.0638 | H49: Warr Margin of Labor | I49: =F22/(F23+F28) -> 0.046553378
B50: Sales Tax | E50: 0.0725 | F50: =E50*F29 -> 3094.3461 | H50: Materials/Ton | I50: =(F25+F26+F27)/D11 -> 2222.9847
E51: Total Profit & Tax | F51: =SUM(F47:F50) -> 13467.258 | H51: Job Cost/Ton | I51: =F52/D11 -> 7576.3112
B52: TOTAL SELLING PRICE | F52: =F51+F46+F35 -> 90915.735 | H52: Net Profit | I52: =D48 -> 0.1
J53: =SUM(J45:J51) -> 1
F55: =0.7*F52 -> 63641.014 | H55: 23200 | I55: 21300
F56: =0.3*F52 -> 27274.72 | H56: 9950 | I56: 9150
H57: =SUM(H55:H56) -> 33150 | I57: =SUM(I55:I56) -> 30450

Sheet Rough Labor
A1: Rough In Labor
A3: Builder | B3: =Summary!B3 -> Bird Dog Group | E3: Model | F3: =Summary!F3 -> 0
A4: Lot | B4: =Summary!B4 -> 0 | E4: Elevation | F4: =Summary!F4 -> 0
A5: Subdivision | B5: =Summary!B5 -> 0
A6: Customer | B6: =Summary!B6 -> Ebert
A7: Address | B7: =Summary!B7 -> 2440 Beretania Circle
A8: City/St/Zip | B8: =Summary!B8 -> Charlotte, NC
A10: Qty | B10: $/Ea | C10: Item | F10: Exten
A11: =Summary!D11 -> 12 | B11: 50 | C11: Tonnage (Outdoor Unit Only) | F11: =A11*B11 -> 600
A12: 2 | B12: 150 | C12: Set Air Handler - Attic | F12: =A12*B12 -> 300
B13: 150 | C13: Set Air Handler - Inside Mechanical Room | F13: =A13*B13 -> 0
A14: 2 | B14: 150 | C14: Set Air Handler - Crawl | F14: =A14*B14 -> 300
A15: 62 | B15: 20 | C15: Supply Drop (Flex, Collar, Elbow, Mastic, Cover) | F15: =A15*B15 -> 1240
A16: 16 | B16: 25 | C16: Return Drop (Flex, Collar, Elbow, Mastic, Cover) | F16: =A16*B16 -> 400
A17: 16 | B17: 15 | C17: Return Box Framing | F17: =A17*B17 -> 240
B18: 25 | C18: Return Jumper Duct | F18: =A18*B18 -> 0
A19: 4 | B19: 10 | C19: Wye | F19: =A19*B19 -> 40
A20: 9 | B20: 35 | C20: Supply Distribution Box - Large | F20: =A20*B20 -> 315
A21: 8 | B21: 15 | C21: Zone Damper (Includes Thermostat Wire) | F21: =A21*B21 -> 120
A22: 3 | B22: 35 | C22: Barometric Bypass | F22: =A22*B22 -> 105
B23: 30 | C23: Supply Plenum Horizontal Duct (4' Only) | F23: =A23*B23 -> 0
B24: 30 | C24: Supply Plenum Horizontal Duct (Each Additional 4' Only) | F24: =A24*B24 -> 0
A25: 12 | B25: 15 | C25: Exhaust Fan (RI Box, Duct, Cap) | F25: =A25*B25 -> 180
A26: 2 | B26: 55 | C26: Dryer Vent - Ducted | F26: =A26*B26 -> 110
B27: 10 | C27: Dryer Vent - Wall Cap Only | F27: =A27*B27 -> 0
A28: 2 | B28: 10 | C28: Laundry Room Transfer Grill | F28: =A28*B28 -> 20
A29: 4 | B29: 30 | C29: Copper Lineset (50' Max) | F29: =A29*B29 -> 120
A30: 2 | B30: 35 | C30: Copper Lineset (Ea Additional 25' Adder) | F30: =A30*B30 -> 70
A31: 4 | B31: 25 | C31: Pressure Test on Copper | F31: =A31*B31 -> 100
A32: 9 | B32: 20 | C32: Thermostat Wire - AHU to Wall Mount Location | F32: =A32*B32 -> 180
B33: 15 | C33: Kitchen Range Vent - 6" Through Wall | F33: =A33*B33 -> 0
B34: 55 | C34: Kitchen Range Vent - Interior 6" Vented TO Wall | F34: =A34*B34 -> 0
B35: 65 | C35: Kitchen Range Vent - Interior 7"-8" Vented TO Wall | F35: =A35*B35 -> 0
A36: 1 | B36: 110 | C36: Kitchen Range Vent - Interior 10" Vented TO Wall | F36: =A36*B36 -> 110
A37: 1 | B37: 40 | C37: Make Up Air - Kitchen Range Vent | F37: =A37*B37 -> 40
A38: 2 | B38: 65 | C38: Flue Exhaust Pipe - Water Heater Only | F38: =A38*B38 -> 130
A39: 4 | B39: 75 | C39: Flue Exhaust Pipe - Gas Furnace Only | F39: =A39*B39 -> 300
B40: 65 | C40: Combustion Air Duct | F40: =A40*B40 -> 0
A41: 4 | B41: 75 | C41: ERV | F41: =A41*B41 -> 300
A42: 4 | B42: 100 | C42: Drive Time beyond 1 hour | F42: =A42*B42 -> 400
A43: 4 | B43: 25 | C43: Media Filter Cabinet | F43: =A43*B43 -> 100
B44: 25 | C44: Humidifier - Bypass | F44: =A44*B44 -> 0
A45: 1 | B45: 25 | C45: MUA Broan | F45: =A45*B45 -> 25
E47: Total | F47: =SUM(F11:F46) -> 5845

Sheet Trim Labor
A1: Finish / Trim Labor
A3: Builder | B3: =Summary!B3 -> Bird Dog Group | E3: Model | F3: =Summary!F3 -> 0
A4: Lot | B4: =Summary!B4 -> 0 | E4: Elevation | F4: =Summary!F4 -> 0
A5: Subdivision | B5: =Summary!B5 -> 0
A6: Customer | B6: =Summary!B6 -> Ebert
A7: Address | B7: =Summary!B7 -> 2440 Beretania Circle
A8: City/St/Zip | B8: =Summary!B8 -> Charlotte, NC
A10: Qty | B10: $/Ea | C10: Item | F10: Exten
A11: ='Rough Labor'!A11 -> 12 | B11: 5 | C11: Tonnage (Outdoor Unit Only) | F11: =A11*B11 -> 60
A12: ='Rough Labor'!A12+'Rough Labor'!A13+'Rough Labor'!A14 -> 4 | B12: 20 | C12: Set Outdoor Unit (Includes Low Voltage Wiring) | F12: =A12*B12 -> 80
A13: ='Rough Labor'!A12+'Rough Labor'!A13+'Rough Labor'!A14 -> 4 | B13: 7.5 | C13: Wire Air Handler (Low Voltage Wiring Only) | F13: =A13*B13 -> 30
A15: ='Rough Labor'!A15 -> 62 | B15: 2 | C15: Supply Register | F15: =A15*B15 -> 124
A16: ='Rough Labor'!A16 -> 16 | B16: 3.5 | C16: Return Grill | F16: =A16*B16 -> 56
A17: ='Rough Labor'!A26+'Rough Labor'!A27 -> 2 | B17: 3.5 | C17: Laundry Room Transfer Grill | F17: =A17*B17 -> 7
A18: ='Rough Labor'!A21 -> 8 | B18: 5 | C18: Zone Damper Wire Connections | F18: =A18*B18 -> 40
A19: ='Rough Labor'!A22 -> 3 | B19: 5 | C19: Barometric Bypass Set Up | F19: =A19*B19 -> 15
A20: ='Rough Labor'!A25 -> 12 | B20: 5 | C20: Exhaust Fan Motor and Cover Install | F20: =A20*B20 -> 60
A21: ='Rough Labor'!A25 -> 12 | B21: 2 | C21: Exhaust Fan Wall/Soffit Cap Verification | F21: =A21*B21 -> 24
A22: ='Rough Labor'!A26+'Rough Labor'!A27 -> 2 | B22: 2 | C22: Dryer Vent Wall Cap Verifiication | F22: =A22*B22 -> 4
F23: =A23*B23 -> 0
A24: ='Rough Labor'!A12+'Rough Labor'!A13+'Rough Labor'!A14 -> 4 | B24: 7.5 | C24: Copper Connections Outside (per system) | F24: =A24*B24 -> 30
A25: ='Rough Labor'!A12+'Rough Labor'!A13+'Rough Labor'!A14 -> 4 | B25: 7.5 | C25: Copper Connections Inside (per system) | F25: =A25*B25 -> 30
A26: ='Rough Labor'!A12+'Rough Labor'!A13+'Rough Labor'!A14 -> 4 | B26: 15 | C26: Vacuum Lineset | F26: =A26*B26 -> 60
A27: ='Rough Labor'!A32 -> 9 | B27: 6 | C27: Thermostat Wiring and Mounting (per Thermostat | F27: =A27*B27 -> 54
F28: =A28*B28 -> 0
A29: ='Rough Labor'!A33+'Rough Labor'!A34+'Rough Labor'!A35+'Rough Labor'!A36 -> 1 | B29: 24 | C29: Kitchen Range Vent Connection | F29: =A29*B29 -> 24
B30: 30 | C30: Kitchen Range Hood Mount | F30: =A30*B30 -> 0
A31: 1 | B31: 250 | C31: Kitchen Range Hood Mount - Canopy | F31: =A31*B31 -> 250
A32: 1 | B32: 15 | C32: Make Up Air Wiring | F32: =A32*B32 -> 15
A33: 1 | B33: 55 | C33: Third Floor Adder | F33: =A33*B33 -> 55
F34: =A34*B34 -> 0
B35: 25 | C35: Reinstall Condensate Drain | F35: =A35*B35 -> 0
B36: 20 | C36: Extend Lineset for Outdoor Unit, Braze | F36: =A36*B36 -> 0
B37: 25 | C37: Braze Lineset in Attic Space | F37: =A37*B37 -> 0
B38: 20 | C38: Uncover Return, Supply, or Laundry Grill | F38: =A38*B38 -> 0
B39: 50 | C39: Find Leak or Kinked Lineset - Braze and Pressure Test | F39: =A39*B39 -> 0
B40: 40 | C40: Level Outdoor Unit beyond normal | F40: =A40*B40 -> 0
A41: 4 | B41: 50 | C41: Drive Time beyond 1 hour | F41: =A41*B41 -> 200
B42: 50 | C42: Relocate Exhaust Fan - Reconnect Ductworki | F42: =A42*B42 -> 0
B43: 25 | C43: Uncover Thermostat Wire - Each | F43: =A43*B43 -> 0
B44: 75 | C44: Install Outdoor Unit Only (inclues trip Charge) | F44: =A44*B44 -> 0
E46: Total | F46: =SUM(F11:F45) -> 1218

Sheet Gas PIpe
A1: Gas Pipe
A3: Builder | B3: =Summary!B3 -> Bird Dog Group | E3: Model | F3: =Summary!F3 -> 0
A4: Lot | B4: =Summary!B4 -> 0 | E4: Elevation | F4: =Summary!F4 -> 0
A5: Subdivision | B5: =Summary!B5 -> 0
A6: Customer | B6: =Summary!B6 -> Ebert
A7: Address | B7: =Summary!B7 -> 2440 Beretania Circle
A8: City/St/Zip | B8: =Summary!B8 -> Charlotte, NC
A10: Qty | B10: $/Ea | C10: Item | F10: Exten
A11: =Summary!D11 -> 12 | B11: 5 | C11: Tonnage | F11: =A11*B11 -> 60
A12: 3 | B12: 65 | C12: Meter / House Set Up | F12: =A12*B12 -> 195
A13: 20 | B13: 40 | C13: Per Gas Opening (Furnace, WH, FP, Range, Etc) | F13: =A13*B13 -> 800
A14: 4 | B14: 60 | C14: Per Gas Opening - Tankless WH | F14: =A14*B14 -> 240
A15: 3 | B15: 30 | C15: Upsize Gas Main to Manifold - ½" up to ¾" CSST | F15: =A15*B15 -> 90
A16: 5 | B16: 30 | C16: Upsize Home Room Gas Line - ½" up to ¾" CSST | F16: =A16*B16 -> 150
B18: 50 | C18: Log Lighter - Includes Key Valve | F18: =A18*B18 -> 0
A19: 5 | B19: 15 | C19: Manifold | F19: =A19*B19 -> 75
A20: 2 | B20: 30 | C20: Appliance Box | F20: =A20*B20 -> 60
A21: 5 | B21: 30 | C21: Key Valve | F21: =A21*B21 -> 150
F22: =A22*B22 -> 0
A23: 7 | B23: 50 | C23: Gas Lantern Set Up (Per Lantern) | F23: =A23*B23 -> 350
F24: =A24*B24 -> 0
A25: 5 | B25: 25 | C25: Home Run Gas Line Length Adder (25' - 50') | F25: =A25*B25 -> 125
A26: 8 | B26: 50 | C26: Home Run Gas Line Length Adder (51' -100') | F26: =A26*B26 -> 400
A27: 7 | B27: 100 | C27: Home Run Gas Line Length Adder (100'+) | F27: =A27*B27 -> 700
F28: =A28*B28 -> 0
A29: 4 | B29: 30 | C29: Air Test - Pressure | F29: =A29*B29 -> 120
F30: =A30*B30 -> 0
B31: 50 | C31: Drive Time beyond 1 hour | F31: =A31*B31 -> 0
B32: 25 | C32: Uncover Appliance Box | F32: =A32*B32 -> 0
B33: 75 | C33: Re Pressure Air Test (Includes Trip Charge) | F33: =A33*B33 -> 0
B34: 55 | C34: Third Floor Adder | F34: =A34*B34 -> 0
B35: 50 | C35: Find Leak - Gas Line | F35: =A35*B35 -> 0
E38: Total | F38: =SUM(F11:F37) -> 3515
E40: 0 | F40: Dryer
E41: 2 | F41: Fireplace - Indoor
E42: 1 | F42: Fireplace - Outdoor
E43: 2 | F43: Future Outdoor Opening
E44: 4 | F44: Gas Furnace
E45: 1 | F45: Outdoor Grill
E46: 2 | F46: Outdoor Range
E47: 1 | F47: Range
F48: Water Heater
E49: 3 | F49: Water Heater - Tankless
E50: 1 | F50: Generator
E51: 7 | F51: Gas Lantern
B75: A4AH6E19A1B30A 1.5 TON AIR HANDLER-RT
B77: A4AH4E30A1B30A 2/2.5 TON AIR HANDLER-RT
B584: 4X12 ADJ GAS BVENT PIPE
B665: 10X4 2W 2 WAY REG WHITE
B828: 1/2 COPPER CLAD 2H STRP
B830: 1/2 SS HOSE CLW 3/8 - 7/8

Sheet Materials
A1: MATERIALS | I1: 10000 | J1: Carrier Equipment | L1: 20000 | M1: Metal Fittings | O1: 29000 | P1: Cu and Refrig
I2: 12000 | J2: Run Tru Equipment | L2: 23000 | M2: Flex and Pipe | O2: 30000 | P2: Finish
A3: Builder | B3: =Summary!B3 -> Bird Dog Group | E3: Model | F3: =Summary!F3 -> 0 | I3: 13000 | J3: Trane Equipment | L3: 24000 | M3: Non Metal Fittings | O3: 32000 | P3: Quickflash
A4: Lot | B4: =Summary!B4 -> 0 | E4: Elevation | F4: =Summary!F4 -> 0 | I4: 15000 | J4: Lennox Equipment | L4: 25000 | M4: Exhaust Fans | O4: 35000 | P4: Fire Dampers
A5: Subdivision | B5: =Summary!B5 -> 0 | I5: 17000 | J5: Mini Split | L5: 26000 | M5: Caps | O5: 39000 | P5: Supplies-Inventoried
A6: Customer | B6: =Summary!B6 -> Ebert | I6: 17600 | J6: Drain Pans | L6: 26500 | M6: Furnace Fittings | O6: 40000 | P6: Supplies-Non-inventoried
A7: Address | B7: =Summary!B7 -> 2440 Beretania Circle | I7: 18000 | J7: Plenums and Boxes | L7: 27000 | M7: Controls & Zoning | O7: 50000 | P7: Gas
A8: City/St/Zip | B8: =Summary!B8 -> Charlotte, NC | I8: 18500 | J8: Fab Items | L8: 28000 | M8: BVENT | O8: 60000 | P8: Service
O9: 70000 | P9: Tools
A10: Part No | B10: Description | C10: Quantity | D10: Net Price | E10: UM | F10: Total
A11: 10100 | B11: FJ4DNXA18L00 1.5 TON AIR HANDLER | D11: 441 | E11: each | F11: =C11*D11 -> 0
A12: 10110 | B12: FJ4DNXB24L00 2 TON AIR HANDLER | D12: 464 | E12: each | F12: =C12*D12 -> 0
A13: 10120 | B13: FJ4DNXB30L00 2.5 TON AIR HANDLER | D13: 488 | E13: each | F13: =C13*D13 -> 0
A14: 10130 | B14: FJ4DNXB36L00 3 TON AIR HANDLER | D14: 491 | E14: each | F14: =C14*D14 -> 0
A15: 10140 | B15: FJ4DNXC42L00 3.5 AIR HANDLER | D15: 632 | E15: each | F15: =C15*D15 -> 0
A16: 10150 | B16: FJ4DNXC48L00 4 TON AIR HANDLER | D16: 635 | E16: each | F16: =C16*D16 -> 0
A17: 10160 | B17: FJ4DNXD60L00 5 TON AIR HANDLER | D17: 768 | E17: each | F17: =C17*D17 -> 0
A18: 10200 | B18: 58SB0A070E17--12 80 GAS FURNACE | D18: 409 | E18: each | F18: =C18*D18 -> 0
A19: 10210 | B19: 58SB0A090E21--16 80 GAS FURNACE | D19: 437 | E19: each | F19: =C19*D19 -> 0
A20: 10220 | B20: 58SB0A090E21--20 80 GAS FURNACE | D20: 461 | E20: each | F20: =C20*D20 -> 0
A21: 10230 | B21: 58SB0B045M14--12 80 GAS FURNACE | D21: 421 | E21: each | F21: =C21*D21 -> 0
A22: 10240 | B22: 58SB0B070M14--12 80 GAS FURNACE | D22: 421 | E22: each | F22: =C22*D22 -> 0
... A213: 17120 | B213: E LITE EQUIPMENT PAD 18X38X3 | D213: 40.05 | E213: each | F213: =C213*D213 -> 0
A214: 17200 | B214: CONDENSATE PUMP PRO CP 225 | C214: 2 | D214: 45.44 | E214: each | F214: =C214*D214 -> 90.88
A215: 17210 | B215: 3/8 x 1/2 Barb x MIP - 701-012D | D215: 3.85 | E215: each | F215: =C215*D215 -> 0
A216: 17220 | B216: 3/8 x 3/4 Barb x MIP | C216: 2 | D216: 4.2 | E216: each | F216: =C216*D216 -> 8.4
A217: 17230 | B217: 1/2 x 3/4 Barb x MIP - 701-002D | D217: 3.25 | E217: each | F217: =C217*D217 -> 0
A218: 17500 | B218: 32X32X3 PLASTIC EQUIP PAD | D218: 47.93 | E218: each | F218: =C218*D218 -> 0
A219: 17510 | B219: 36X36X3 PLASTIC EQUIP PAD | C219: 4 | D219: 32.95 | E219: each | F219: =C219*D219 -> 131.8
A220: 17520 | B220: 36X40X3 PLASTIC EQUIP PAD | E220: each | F220: =C220*D220 -> 0
A221: 17600 | B221: 24X34 24GA DRN PAN NO HOLE | D221: 35.75 | E221: each | F221: =C221*D221 -> 0
A222: 17610 | B222: 30X34 24GA DRN PAN NO HOLE | D222: 36.38 | E222: each | F222: =C222*D222 -> 0
A223: 17620 | B223: 30X36 24GA DRN PAN | E223: each | F223: =C223*D223 -> 0
A224: 17630 | B224: 30X60 24GA DRN PAN | D224: 48.62 | E224: each | F224: =C224*D224 -> 0
A225: 17640 | B225: 32X70 24GA DRN PAN | E225: each | F225: =C225*D225 -> 0
A226: 17650 | B226: 34X75 24GA DRN PAN | D226: 61.95 | E226: each | F226: =C226*D226 -> 0
A227: 17660 | B227: 36X80 24GA DRN PAN | C227: 2 | D227: 65.54 | E227: each | F227: =C227*D227 -> 131.08
A228: 17670 | B228: 12X10X3-1/2 GAS BOX - NO HOLE | C228: 3 | D228: 9 | E228: each | F228: =C228*D228 -> 27
A229: 18000 | B229: 11X17X24 DB PLENUM W CAP R8 | D229: 44.68 | E229: each | F229: =C229*D229 -> 0
A230: 18010 | B230: 11X17X24 DB SLEEVE - NO CAP R8 | D230: 36.76 | E230: each | F230: =C230*D230 -> 0
A231: 18020 | B231: 11X17X48 DB PLENUM W CAP R8 | D231: 59.87 | E231: each | F231: =C231*D231 -> 0
A232: 18030 | B232: 11-1/4X18X24 DB PLENUM W CAP R8 | D232: 31.08 | E232: each | F232: =C232*D232 -> 0
A233: 18040 | B233: 11-1/4X18X24 DB SLEEVE NO CAP R8 | D233: 30 | E233: each | F233: =C233*D233 -> 0
A234: 18050 | B234: 11-1/4X18X48 DB PLENUM W CAP R8 | D234: 62.16 | E234: each | F234: =C234*D234 -> 0
A235: 18060 | B235: 14-1/2X18X24 DB PLENUM W CAP R8 | D235: 33.46 | E235: each | F235: =C235*D235 -> 0
A236: 18070 | B236: 14-1/2X18X48DB SLEEVE NO CAP R8 | D236: 32 | E236: each | F236: =C236*D236 -> 0
A237: 18080 | B237: 14-1/2X18X48 DB PLENUM W CAP R8 | D237: 62.58 | E237: each | F237: =C237*D237 -> 0
A238: 18090 | B238: 14-3/4X17X24 DB PLENUM W CAP R4 | C238: 1 | D238: 42 | E238: each | F238: =C238*D238 -> 42
A239: 18100 | B239: 14-3/4X17X24 DB SLEEVE - NO CAP R8 | D239: 38.8 | E239: each | F239: =C239*D239 -> 0
A240: 18110 | B240: 14-3/4X17X48 DB PLENUM W CAP R4 | C240: 2 | D240: 53.94 | E240: each | F240: =C240*D240 -> 107.88
A241: 18120 | B241: 17X17X24 DB PLENUM W CAP R8 | D241: 47.97 | E241: each | F241: =C241*D241 -> 0
A242: 18130 | B242: 17X17X24 DB SLEEVE - NO CAP R8 | D242: 40.02 | E242: each | F242: =C242*D242 -> 0
A243: 18140 | B243: 17X17X48 DB PLENUM W CAP R8 | D243: 66.39 | E243: each | F243: =C243*D243 -> 0
A244: 18150 | B244: 18X18X24 DB PLENUM W CAP R8 | D244: 35.27 | E244: each | F244: =C244*D244 -> 0
A245: 18160 | B245: 18X18X24 DB SLEEVE NO CAP R8 | D245: 34 | E245: each | F245: =C245*D245 -> 0
A246: 18170 | B246: 18X18X48 DB PLENUM W CAP R8 | D246: 70.47 | E246: each | F246: =C246*D246 -> 0
A247: 18180 | B247: 19-3/4X17X24 DB PLENUM W CAP R8 | C247: 2 | D247: 50.18 | E247: each | F247: =C247*D247 -> 100.36
A248: 18190 | B248: 19-3/4X17X24 DB SLEEVE NO CAP R8 | C248: 2 | D248: 41.51 | E248: each | F248: =C248*D248 -> 83.02
A249: 18200 | B249: 19-3/4X17X48 DB PLENUM W CAP R8 | C249: 2 | D249: 70.12 | E249: each | F249: =C249*D249 -> 140.24
A250: 18210 | B250: 12x12x48 DB CAP MALE END R4 | D250: 31.74 | E250: each | F250: =C250*D250 -> 0
A251: 18220 | B251: 12x12x48 DB CAP FEMALE END R4 | D251: 31.74 | E251: each | F251: =C251*D251 -> 0
A252: 18230 | B252: 12x12x48 DB NO CAP R4 | D252: 30.55 | E252: each | F252: =C252*D252 -> 0
A253: 18240 | B253: 21X21X24 DB PLENUM W CAP | D253: 42.34 | E253: each | F253: =C253*D253 -> 0
A254: 18250 | B254: 21X2IX24 DB SLEEVE NO CAP R8 | D254: 40 | E254: each | F254: =C254*D254 -> 0
A255: 18260 | B255: 2IX21X48 DB PLENUM W CAP R8 | D255: 74.7 | E255: each | F255: =C255*D255 -> 0
A256: 18270 | B256: METAL DIST TRIANGLE | D256: 55 | E256: each | F256: =C256*D256 -> 0
A257: 18280 | B257: LRG DB TRIANGLE DIST | C257: 9 | D257: 43.79 | E257: each | F257: =C257*D257 -> 394.11
A258: 18290 | B258: 12-1/2 X 12-1/2 X 12 METAL BOX (UNINSUL) | D258: 12.04 | E258: each | F258: =C258*D258 -> 0
A259: 18300 | B259: 14-1/2 X 14-1/2 X 12 METAL BOX (UNINSUL) | D259: 14.57 | E259: each | F259: =C259*D259 -> 0
A260: 18310 | B260: 16-1/2X16-1/2 X 12 METAL BOX (UNINSUL) | D260: 15.26 | E260: each | F260: =C260*D260 -> 0
A261: 18320 | B261: 20-1/2 X 14-1/2 X 12 METAL BOX (UNINSUL) | D261: 17.7 | E261: each | F261: =C261*D261 -> 0
A262: 18330 | B262: 24-1/2 X 12-1/2 X 12 METAL BOX (UNINSUL) | D262: 18.95 | E262: each | F262: =C262*D262 -> 0
A263: 18340 | B263: 25-1/2 X14-1/2 X 12 METAL BOX (UNINSUL) | D263: 19.9 | E263: each | F263: =C263*D263 -> 0
A264: 18350 | B264: 12-1/2 X 12-1/2 X 12 METAL BOX R8 | C264: 4 | D264: 19.92 | E264: each | F264: =C264*D264 -> 79.68
A265: 18360 | B265: 14-1/2 X 14-1/2 x 12 METAL BOX R8 | C265: 3 | D265: 24.62 | E265: each | F265: =C265*D265 -> 73.86
A266: 18370 | B266: 16-1/2 X 16-1/2 X 12 METAL BOX R8 | D266: 29.73 | E266: each | F266: =C266*D266 -> 0
A267: 18380 | B267: 16-1/2 X 25-1/2 X 12 RTN AIR BOX R8 | D267: 31.9 | E267: each | F267: =C267*D267 -> 0
A268: 18390 | B268: 20-1/2 X 14-1/2 X 12 METAL BOX R8 | C268: 1 | D268: 32.9 | E268: each | F268: =C268*D268 -> 32.9
A269: 18400 | B269: 20-1/2 X 20-1/2 X 12 METAL BOX R8 | C269: 2 | D269: 41.22 | E269: each | F269: =C269*D269 -> 82.44
A270: 18410 | B270: 24-1/2 X 12-1/2 X 12 METAL BOX R8 | D270: 35.27 | E270: each | F270: =C270*D270 -> 0
A271: 18420 | B271: 25-1/2 X 14-1/2 X 12 R8 METAL BOX R8 | D271: 53.94 | E271: each | F271: =C271*D271 -> 0
A272: 18430 | B272: 25-1/2 X 16-1/2 X 12 METAL BOX R8 | D272: 43.13 | E272: each | F272: =C272*D272 -> 0
A273: 18440 | B273: 25-1/2 X 20-1/2 X 12 METAL BOX R8 | C273: 1 | D273: 49.7 | E273: each | F273: =C273*D273 -> 49.7
A274: 18450 | B274: 14-1/2X24X18 PLATFORM BOX | D274: 40.62 | E274: each | F274: =C274*D274 -> 0
A275: 18460 | B275: 14-3/4X22X18 PLATFORM BOX | D275: 53.98 | E275: each | F275: =C275*D275 -> 0
A276: 18470 | B276: 17-3/4X24X18 PLATFORM BOX | C276: 1 | D276: 47.33 | E276: each | F276: =C276*D276 -> 47.33
A277: 18480 | B277: 18-3/4X22X18 PLATFORM BOX | D277: 52.44 | E277: each | F277: =C277*D277 -> 0
A278: 18490 | B278: 21X24X18 PLATFORM BOX | D278: 54.05 | E278: each | F278: =C278*D278 -> 0
A279: 18500 | B279: 21-1/4X22X18 PLATFORM BOX | D279: 66.62 | E279: each | F279: =C279*D279 -> 0
A280: 18510 | B280: 23-3/4X22X18 PLATFORM BOX | D280: 71.51 | E280: each | F280: =C280*D280 -> 0
A281: 18520 | B281: 24-1/2X24X22 PLATFORM BOX | D281: 79.81 | E281: each | F281: =C281*D281 -> 0
A282: 18530 | B282: 25X24X22 PLATFORM BOX | D282: 89.3 | E282: each | F282: =C282*D282 -> 0
A283: 18540 | B283: 4X4 WALL CAP HOOD - LINESET COVER | D283: 7 | E283: each | F283: =C283*D283 -> 0
A284: 18550 | B284: IX48X120 2" R8 DB 6 SHT | E284: each | F284: =C284*D284 -> 0
A285: 18560 | B285: 48X96 24 GA SHEET METAL | E285: each | F285: =C285*D285 -> 0
A286: 18570 | B286: 48X96 26 GA SHEET METAL | D286: 41.17 | E286: each | F286: =C286*D286 -> 0
A287: 18580 | B287: 4X4 METAL STRIP 48" LONG | C287: 4 | D287: 3 | E287: each | F287: =C287*D287 -> 12
A288: 18590 | B288: 1/2" x 1-1/2"-48" DRYWALLFRAME | D288: 2.75 | E288: each | F288: =C288*D288 -> 0
A289: 18600 | B289: 120 26GA S CLEAT | D289: 5.95 | E289: each | F289: =C289*D289 -> 0
A290: 18610 | B290: 120 26GA DRV CLEAT | C290: 8 | D290: 3.16 | E290: each | F290: =C290*D290 -> 25.28
...

Sheet Calc
A2: Owner's Bath 209 3088 1567 144 95 | C2: 144 | D2: =C2*C$19 -> 118.58824
A3: Owner's Suite 303 4551 4152 212 251 | C3: 251 | D3: =C3*C$19 -> 206.70588
A4: Family Room 431 3168 1807 148 109 | C4: 148 | D4: =C4*C$19 -> 121.88235
A5: Owner's WIC 212 3515 2359 164 143 | C5: 164 | D5: =C5*C$19 -> 135.05882
A6: Foyer 122 1468 1258 68 76 | C6: 76 | D6: =C6*C$19 -> 62.588235 | F6: =D13+D14+D15+D16+D17+D11+D12 -> 534.47059
A7: Study 206 2786 2160 130 131 | C7: 131 | D7: =C7*C$19 -> 107.88235 | F7: =D18-F6 -> 865.52941
A8: Study Bath 91 1319 729 61 44 | C8: 61 | D8: =C8*C$19 -> 50.235294
A9: Kitchen 268 330 1170 15 71 | C9: 71 | D9: =C9*C$19 -> 58.470588
A10: Scullery 104 118 44 5 3 | C10: 5 | D10: =C10*C$19 -> 4.1176471
A11: Casual Dining 200 4045 3473 188 210 | C11: 210 | D11: =C11*C$19 -> 172.94118
A12: 1st Stair 160 2036 1697 95 103 | C12: 103 | D12: =C12*C$19 -> 84.823529
A13: Entry Hall 112 2847 1778 133 107 | C13: 107 | D13: =C13*C$19 -> 88.117647
A14: Laundry 109 132 485 6 29 | C14: 29 | D14: =C14*C$19 -> 23.882353
A15: 1st Hall 160 0 0 0 0 | C15: 0 | D15: =C15*C$19 -> 0
A16: Billards | C16: 145 | D16: =C16*C$19 -> 119.41176
A17: Lounge | C17: 55 | D17: =C17*C$19 -> 45.294118
C18: =SUM(C2:C17) -> 1700 | D18: =SUM(D2:D17) -> 1400
C19: =C20/C18 -> 0.82352941
C20: 1400
A22: Command Center 70 927 664 35 36 | C22: 36 | D22: =C22*C$39 -> 40.862656
A23: Hall Up 285 909 825 34 45 | C23: 45 | D23: =C23*C$39 -> 51.07832
A24: 2nd Stair 160 4948 3553 187 193 | C24: 193 | D24: =C24*C$39 -> 219.06924
A25: W/D Up 32 0 0 0 0 | C25: 0 | D25: =C25*C$39 -> 0
A26: Suite 3 Bath 98 1993 1187 75 64 | C26: 75 | D26: =C26*C$39 -> 85.130533
A27: Suite 2 Bath 75 224 129 8 7 | C27: 8 | D27: =C27*C$39 -> 9.0805902
A28: Suite 2 WIC 40 120 69 5 4 | C28: 5 | D28: =C28*C$39 -> 5.6753689
A29: Suite 2 165 1854 1429 70 78 | C29: 78 | D29: =C29*C$39 -> 88.535755
A30: Bonus Room 431 4092 3143 154 171 | C30: 171 | D30: =C30*C$39 -> 194.09762
A31: Suite 3 WIC 33 97 56 4 3 | C31: 4 | D31: =C31*C$39 -> 4.5402951
A32: Suite 3 216 2855 1879 108 102 | C32: 108 | D32: =C32*C$39 -> 122.58797
A33: Suite 4 WIC 34 101 58 4 3 | C33: 4 | D33: =C33*C$39 -> 4.5402951
... A35: Suite 4 216 3356 2016 127 110 | C35: 110 | D35: =C35*C$39 -> 124.85812
A36: Unfinished Storage | D36: =C36*C$39 -> 0
A37: Future Expansion | D37: =C37*C$39 -> 0
C38: =SUM(C22:C37) -> 881 | D38: =SUM(D22:D37) -> 1000
C39: =C40/C38 -> 1.1350738
C40: 1000

Sheet Sheet2
A1: MATERIALS | I1: 1000 | J1: Boxes | L1: 2300 | M1: Cu and Refrig
I2: 1000 | J2: Metal Fittings | L2: 2500 | M2: Finish
A3: Builder | B3: =Summary!B3 -> Bird Dog Group | E3: Model | F3: =Summary!F3 -> 0 | I3: 1400 | J3: Furnace Fittings | L3: 2800 | M3: BVENT
A4: Lot | B4: =Summary!B4 -> 0 | E4: Elevation | F4: =Summary!F4 -> 0 | I4: 1500 | J4: Flex and Pipe | L4: 3000 | M4: Caps
A5: Subdivision | B5: =Summary!B5 -> 0 | I5: 2000 | J5: Non Metal Fittings | L5: 4000 | M5: Supplies
A6: Customer | B6: =Summary!B6 -> Ebert | I6: 2100 | J6: Exhaust Fans | L6: 5000 | M6: Other
A7: Address | B7: =Summary!B7 -> 2440 Beretania Circle | I7: 2200 | J7: Controls & Zoning | L7: 6000 | M7: Service | O7: 7000 | P7: Gas
A8: City/St/Zip | B8: =Summary!B8 -> Charlotte, NC
A10: Part No | B10: Description | C10: Box Qty | D10: Quantity | E10: Net Price | F10: UM | G10: Total
A11: 10000 | B11: 11-1/4X18X24 DB PLENUM W CAP R8 | E11: 31.08 | F11: EA | G11: =D11*E11 -> 0
A12: 10005 | B12: 11-1/4X18X24 DB SLEEVE NO CAP R8 | E12: 30 | F12: EA | G12: =D12*E12 -> 0
A13: 10010 | B13: 11-1/4X18X48 DB PLENUM W CAP R8 | E13: 62.16 | F13: EA | G13: =D13*E13 -> 0
A14: 10020 | B14: 14-1/2X18X24 DB PLENUM W CAP R8 | D14: 1 | E14: 33.46 | F14: EA | G14: =D14*E14 -> 33.46
A15: 10025 | B15: 14-1/2X18X48DB SLEEVE NO CAP R8 | D15: 1 | E15: 32 | F15: EA | G15: =D15*E15 -> 32
A16: 10030 | B16: 14-1/2X18X48 DB PLENUM W CAP R8 | E16: 62.58 | F16: EA | G16: =D16*E16 -> 0
A17: 10040 | B17: 18X18X24 DB PLENUM W CAP R8 | E17: 35.27 | F17: EA | G17: =D17*E17 -> 0
A18: 10045 | B18: 18X18X24 DB SLEEVE NO CAP R8 | E18: 34 | F18: EA | G18: =D18*E18 -> 0
A19: 10050 | B19: 18X18X48 DB PLENUM W CAP R8 | E19: 70.47 | F19: EA | G19: =D19*E19 -> 0
A20: 10060 | B20: 21X21X24 DB PLENUM W CAP | E20: 42.34 | F20: EA | G20: =D20*E20 -> 0
A21: 10065 | B21: 21X2IX24 DB SLEEVE NO CAP R8 | E21: 40 | F21: EA | G21: =D21*E21 -> 0
A22: 10070 | B22: 2IX21X48 DB PLENUM W CAP R8 | E22: 74.7 | F22: EA | G22: =D22*E22 -> 0
A23: 10075 | B23: 21X21X48 DB SLEEVE -NO CAP R8 | E23: 65 | F23: EA | G23: =D23*E23 -> 0
A24: 10090 | B24: LRG DB TRIANGLE DIST | D24: 2 | E24: 43.79 | F24: EA | G24: =D24*E24 -> 87.58
A25: 10100 | B25: 12-1/2 X 12-1/2 X 12 METAL BOX (UNINSUL) | E25: 12.04 | F25: EA | G25: =D25*E25 -> 0
A26: 10110 | B26: 14-1/2 X 14-1/2 X 12 METAL BOX (UNINSUL) | E26: 14.57 | F26: EA | G26: =D26*E26 -> 0
A27: 10112 | B27: 16-1/2X16-1/2 X 12 METAL BOX (UNINSUL) | E27: 15.26 | F27: EA | G27: =D27*E27 -> 0
A28: 10117 | B28: 20-1/2 X 14-1/2 X 12 METAL BOX (UNINSUL) | E28: 17.7 | F28: EA | G28: =D28*E28 -> 0
A29: 10120 | B29: 24-1/2 X 12-1/2 X 12 METAL BOX (UNINSUL) | D29: 1 | E29: 18.95 | F29: EA | G29: =D29*E29 -> 18.95
A30: 10130 | B30: 25-1/2 X14-1/2 X 12 METAL BOX (UNINSUL) | E30: 19.56 | F30: EA | G30: =D30*E30 -> 0
A31: 10140 | B31: 12-1/2 X 12-1/2 X 12 METAL BOX R8 | E31: 19.92 | F31: EA | G31: =D31*E31 -> 0
A32: 10150 | B32: 14-1/2 X 14-1/2 x 12 METAL BOX R8 | E32: 24.62 | F32: EA | G32: =D32*E32 -> 0
A33: 10160 | B33: 16-1/2 X 16-1/2 X 12 METAL BOX R8 | E33: 29.73 | F33: EA | G33: =D33*E33 -> 0
B34: 16-1/2 X 25-1/2 X 18 RTN AIR BOX R8 | E34: 29.07 | F34: EA | G34: =D34*E34 -> 0
A35: 10170 | B35: 20-1/2 X 14-1/2 X 12 METAL BOX R8 | D35: 1 | E35: 32.9 | F35: EA | G35: =D35*E35 -> 32.9
A36: 10180 | B36: 20-1/2 X 20-1/2 X 12 METAL BOX R8 | E36: 41.22 | F36: EA | G36: =D36*E36 -> 0
A37: 10190 | B37: 24-1/2 X 12-1/2 X 12 METAL BOX R8 | E37: 35.27 | F37: EA | G37: =D37*E37 -> 0
A38: 10200 | B38: 25-1/2 X 14-1/2 X 12 R8 METAL BOX R8 | E38: 53.94 | F38: EA | G38: =D38*E38 -> 0
A39: 10210 | B39: 25-1/2 X 16-1/2 X 12 METAL BOX R8 | E39: 43.13 | F39: EA | G39: =D39*E39 -> 0
A40: 10220 | B40: 25-1/2 X 20-1/2 X 12 METAL BOX R8 | E40: 49.7 | F40: EA | G40: =D40*E40 -> 0
A41: 11000 | B41: 14-1/2X24X18 PLATFORM BOX | E41: 40.62 | F41: EA | G41: =D41*E41 -> 0
A42: 11010 | B42: 17-3/4X24X18 PLATFORM BOX | E42: 47.33 | F42: EA | G42: =D42*E42 -> 0
A43: 11020 | B43: 21X24X18 PLATFORM BOX | E43: 54.05 | F43: EA | G43: =D43*E43 -> 0
A44: 11024 | B44: 23-3/4X22X18 PLATFORM BOX | E44: 0 | F44: EA | G44: =D44*E44 -> 0
A45: 11030 | B45: 24-1/2X24X22 PLATFORM BOX | E45: 79.81 | F45: EA | G45: =D45*E45 -> 0
A46: 11040 | B46: 4X4 METAL STRIP 48" LONG | D46: 1 | E46: 3 | F46: EA | G46: =D46*E46 -> 3
A47: 11050 | B47: 4X4 WALL CAP HOOD - LINESET COVER | E47: 7 | F47: EA | G47: =D47*E47 -> 0
A48: 11060 | B48: 1/2" x 1-1/2"-48" DRYWALLFRAME | E48: 2.75 | F48: EA | G48: =D48*E48 -> 0
A49: 11061 | B49: 12X10X3-1/2 GAS BOX - NO HOLE | E49: 9 | F49: EA | G49: =D49*E49 -> 0
A50: 11063 | B50: 24X34 24GA DRN PAN NO HOLE | E50: 35.75 | F50: EA | G50: =D50*E50 -> 0
A51: 11065 | B51: 30X34 24GA DRN PAN NO HOLE | E51: 36.38 | F51: EA | G51: =D51*E51 -> 0
A52: 11070 | B52: 30X36 24GA DRN PAN | E52: 34.78 | F52: EA | G52: =D52*E52 -> 0
A53: 11080 | B53: 30X60 24GA DRN PAN | D53: 1 | E53: 48.06 | F53: EA | G53: =D53*E53 -> 48.06
A54: 11090 | B54: 32X70 24GA DRN PAN | E54: 61.95 | F54: EA | G54: =D54*E54 -> 0
A55: 11095 | B55: 34X75 24GA DRN PAN | E55: 61.95 | F55: EA | G55: =D55*E55 -> 0
A56: 11100 | B56: 36X80 24GA DRN PAN | E56: 65.54 | F56: EA | G56: =D56*E56 -> 0
A57: 12000 | B57: IX48X120 2" R8 DB 6 SHT cm | E57: 46.25 | F57: EA | G57: =D57*E57 -> 0
A58: 12010 | B58: 48X96 24 GA SHEET METAL | E58: 45.92 | F58: EA | G58: =D58*E58 -> 0
A59: 12020 | B59: 48X96 26 GA SHEET METAL | E59: 41.17 | F59: EA | G59: =D59*E59 -> 0
A60: 13320 | B60: 16 GA ANGLE 2X2 | E60: 22 | F60: EA | G60: =D60*E60 -> 0
A61: 13330 | B61: 100 FT COIL 30 GA GALV HGR STRP | E61: 20.95 | F61: EA | G61: =D61*E61 -> 0
A62: 13340 | B62: 120 26GA S CLEAT | E62: 5.95 | F62: EA | G62: =D62*E62 -> 0
A63: 13350 | B63: 120 26GA DRV CLEAT | D63: 2 | E63: 3.16 | F63: EA | G63: =D63*E63 -> 6.32
A64: 13355 | B64: 120 28GA DRV CLEAT | E64: 3.68 | F64: EA | G64: =D64*E64 -> 0
A65: 20140 | B65: 3X48X50 FSK DUCT WRAP R8 | E65: 34.2342 | F65: EA | G65: =D65*E65 -> 0
A66: 20150 | B66: 2.2X48X75 FSK DUCT WRAP R6 | E66: 94.97 | F66: EA | G66: =D66*E66 -> 0
A67: 12030 | B67: 10X4X4 STRT BOOT | D67: 1 | E67: 3.46 | F67: EA | G67: =D67*E67 -> 3.46
A68: 12040 | B68: 10X4X6 STRT BOOT | D68: 1 | E68: 3.09 | F68: EA | G68: =D68*E68 -> 3.09
A69: 12050 | B69: 12X4X7 STRT BOOT | D69: 1 | E69: 3.98 | F69: EA | G69: =D69*E69 -> 3.98
A70: 12060 | B70: 14X4X8 STRT BOOT | D70: 1 | E70: 5.85 | F70: EA | G70: =D70*E70 -> 5.85
A71: 12070 | B71: 14X6X8 STRT BOOT | E71: 5.18 | G71: =D71*E71 -> 0
A72: 12080 | B72: 14X6X9 STRT BOOT | E72: 9.11 | F72: EA | G72: =D72*E72 -> 0
A73: 12090 | B73: 10X4X4 90 ANGLE BOOT | E73: 4.05 | F73: EA | G73: =D73*E73 -> 0
A74: 12100 | B74: 10X4X6 90 ANGLE BOOT | E74: 3.1 | F74: EA | G74: =D74*E74 -> 0
A75: 12110 | B75: 12X4X7 90 ANGLE BOOT | E75: 4.31 | F75: EA | G75: =D75*E75 -> 0
A76: 12120 | B76: 14X4X8 90 ANGLE BOOT | D76: 2 | E76: 6.95 | F76: EA | G76: =D76*E76 -> 13.9
A77: 12130 | B77: 14X6X8 90 ANGLE BOOT | E77: 5.65 | F77: EA | G77: =D77*E77 -> 0
A78: 12140 | B78: 14X6X9 90 ANGLE BOOT | E78: 9.65 | F78: EA | G78: =D78*E78 -> 0
A79: 12150 | B79: 10X4X4 CNTR END BOOT | E79: 4.65 | F79: EA | G79: =D79*E79 -> 0
A80: 12160 | B80: 10X4X6 CNTR END BOOT | D80: 1 | E80: 4.09 | F80: EA | G80: =D80*E80 -> 4.09
A81: 12170 | B81: 12X4X7 CNTR END BOOT | E81: 5.32 | F81: EA | G81: =D81*E81 -> 0
A82: 12180 | B82: 14X4X8 CNTR END BOOT | E82: 6.89 | F82: EA | G82: =D82*E82 -> 0
A83: 12190 | B83: 14X6X8 CNTR END BOOT | E83: 7.4 | F83: EA | G83: =D83*E83 -> 0
A84: 12200 | B84: 14X6X9 CNTR END BOOT | E84: 7.51 | F84: EA | G84: =D84*E84 -> 0
A85: 12210 | B85: 10X4 BOOT FRM 24 | D85: 3 | E85: 3.32 | F85: EA | G85: =D85*E85 -> 9.96
A86: 12220 | B86: 12X4 BOOT FRM 24 | D86: 1 | E86: 3.31 | F86: EA | G86: =D86*E86 -> 3.31
A87: 12230 | B87: 14X4 BOOT FRM 24 | D87: 3 | E87: 4.53 | F87: EA | G87: =D87*E87 -> 13.59
A88: 12240 | B88: 14X6 BOOT FRM 24 | E88: 4.09 | F88: EA | G88: =D88*E88 -> 0
A89: 12250 | B89: 26 BOOT RAIL | E89: 0.67 | F89: EA | G89: =D89*E89 -> 0
A90: 12260 | B90: 4 MET START COLLAR | E90: 1.16 | F90: EA | G90: =D90*E90 -> 0
A91: 12280 | B91: 6 MET START COLLAR | E91: 1.3 | F91: EA | G91: =D91*E91 -> 0
A92: 12290 | B92: 7 MET START COLLAR | E92: 1.56 | F92: EA | G92: =D92*E92 -> 0
A93: 12300 | B93: 8 MET START COLLAR | E93: 1.75 | F93: EA | G93: =D93*E93 -> 0
A94: 12310 | B94: 9 MET START COLLAR | E94: 2.18 | F94: EA | G94: =D94*E94 -> 0
A95: 12320 | B95: 10 MET START COLLAR | E95: 2.19 | F95: EA | G95: =D95*E95 -> 0
A96: 12330 | B96: 12 MET START COLLAR | D96: 2 | E96: 2.89 | F96: EA | G96: =D96*E96 -> 5.78
A97: 12340 | B97: 14 MET START COLLAR | E97: 3.57 | F97: EA | G97: =D97*E97 -> 0
A98: 12350 | B98: 16 MET START COLLAR | E98: 6.2 | F98: EA | G98: =D98*E98 -> 0
A99: 12360 | B99: 18 MET START COLL | E99: 7.65 | F99: EA | G99: =D99*E99 -> 0
A100: 12370 | B100: 20 MET START COLL | E100: 9.75 | F100: EA | G100: =D100*E100 -> 0
A101: 12380 | B101: 4 DB START COLLAR | D101: 1 | E101: 1.21 | F101: EA | G101: =D101*E101 -> 1.21
...

Sheet On Call
A1: On Call Extra
A3: Date
B5: Qty | C5: Rate | D5: Item | E5: Exten
C6: 75 | D6: On Call Period / Rotating Week/Weekend
C7: 75 | D7: Holiday On Call (Per Night)
C8: 5 | D8: Answer Messages from Service Line
C9: 20 | D9: Walk Through Service Call Over Phone (15 Min max)
A11: Hrs | B11: $/Hr | C11: Address Lot/Subdivision
B12: 20
D22: Total

Sheet Extras
C1: Options and Extras
A8: Cost/Ea | B8: UoM | C8: Item
A9: 250 | B9: Ea | C9: Add One SUPPLY Drop
A10: 375 | B10: Ea | C10: Add One RETURN Opening
A11: 75 | B11: Ea | C11: Upsize One Supply or Return Duct by One Size
A12: 75 | B12: Per | C12: Extend Supply Duct to the Outside Wall
A13: 1650 | B13: Per | C13: Install Zone System
A14: 750 | B14: Ea | C14: Upsize Equipment by One HALF Ton | F14: 19250
A15: 160 | B15: Ea | C15: Add One Fan Only 50 CFM Bath (1667H & 1688F) | F15: 800
A16: 250 | B16: Ea | C16: Add One Fan/Light Combo 50 CFM (2667H & 2688F) | F16: 375
A17: 325 | B17: Ea | C17: Add One Fan Only 80 CFM Bath Fan (N671) | F17: 375
A18: 200 | B18: Ea | C18: Install Combustion Air High Low Round Duct | F18: 1650
A19: 100 | B19: Ea | C19: Install Combustion Air Grilles (North Carolina Only) | F19: =SUM(F14:F18) -> 22450
A20: 100 | B20: Ea | C20: Install Laundry Room Combustion Air Grille
A21: 200 | B21: Ea | C21: Vent Range Hood on Exterior Wall
A22: 380 | B22: Ea | C22: Vent Range Hood on Interior Wall
A23: 650 | B23: Ea | C23: 6" Fresh Air Damper - Duct and Labor Included (Honeywell Y8150 Controller)
A24: 400 | B24: Ea | C24: Dryer Vent Booster
A25: 800 | B25: Ea | C25: Install ½" Log Lighter for a Wood Burning Fireplace
A26: 475 | B26: Ea | C26: Additional Gas Line - (Fireplace, Pation, Range, Dryer, etc) ½" Gas Pipe Opening
A27: 850 | B27: Ea | C27: Add Gas Line to One Appliance (Electric Base House)
A28: 925 | B28: Ea | C28: Add Propane Gas Line to Fireplace Only
A29: 750 | B29: Ea | C29: Add Gas to Gas Water Heater (½" Gas Pipe Opening and 4" Exhaust Vent Pipe)
A30: 885 | B30: Ea | C30: Tankless Water Heater (Upsize to ¾" Gas Line Opening)
A31: Price per House | C31: Tankless Water Heater Vent Extension
A32: 575 | B32: Ea | C32: Add Full or Half Bath to Existing Room (Supply Drop and Fan/Light Combo - 50 CFM)
A33: 250 | B33: Ea | C33: Additional Lineset Extension Up to 15 ft Only
A34: 375 | B34: Ea | C34: Additional Lineset Extension 16 ft to 35 Ft Only
A35: 575 | B35: Ea | C35: Additional Lineset Extension Up to an additional 50 Ft
A36: 1375 | B36: Ea | C36: Honeywell Humidifier (HM509H8910) w/ Compatible Thermostat (TH9421U1002)
A37: 3400 | B37: Ea | C37: Dehumidifier with Ductwork
A38: 3250 | B38: Ea | C38: Dehumidifier without Ductwork
A39: 400 | B39: Ea | C39: Aprilaire 4" Media Air Cleaner - Includes Filter
A40: 1850 | B40: Ea | C40: Sales Office - Includes Ductwork, 4 SA Drop, 1 RA and Builder Supplied Equipment
A41: 150 | B41: Ea | C41: Trip Charge
A42: 175 | B42: Ea | C42: Cabarrus County Permit Increase
A43: 175 | B43: Ea | C43: Iredell County Permit Increase
... A60: 625 | B60: Ea | C60: HVAC Code ADDER - Raleigh

Sheet Time Card
E1: WEEKLY TIMESHEET | L1: Week of:
I4: Employee Name (Print)
A8: DAY | B8: Date | C8: Start Time | D8: Lunch Start | E8: Lunch End | F8: End Time | G8: Reg Hours | H8: Piece Rate Hours | I8: Total Hours Worked | J8: Job Number | K8: LOT | L8: SUBDIVISION / ADDRESS | M8: PAY
A9: MONDAY
A13: TUESDAY
A17: WEDNESDAY
A21: THURSDAY
A25: FRIDAY
A29: SATURDAY
A31: SUNDAY
A33: WEEKLY TOTALS | G33: Reg Hrs | H33: PCR Hrs | I33: Total Hrs | J33: WEEKLY PIECE RATE PAY | M33: Total PCR Pay
A36: Employee Signature | G36: Date | L36: Internal Use Only
A38: Supervisor Signature | G38: Date

Sheet Builder Info Sheet
F1: HVAC / BUILDER INFORMATION SHEET | L1: Date
B6: Lot | J6: Builder
B7: Subdivision | J7: Contact
B8: Customer Name | J8: Email
B9: Address | J9: Address
B10: City / St | J10: City / St
B11: County | J11: Billing Contact
J12: Billing Email
A13: House Faces (Front Door) | E13: N / E / S / W
A15: Wall Type | F15: Roof Type
B16: Wood | D16: R11 | G16: Shingle | I16: R30
B17: Block | D17: R13 | G17: Metal | I17: R38
D18: R17 | G18: Tile | I18: Icynene
D19: Icynene
A20: Window Type
B21: DBL Pane | D21: Reflect
B22: Trip Pane | D22: Low E
A25: HVAC SYSTEM
B26: Qty of Systems | D26: Brand
B27: Electric / Gas
B28: Zoning
A30: Gas Pipe to | C30: Range Vent
B31: Furnace | D31: Location
B32: Water Heater | D32: Size
B33: Dryer | D33: Hang Hood
B34: Range
B35: Patio
B36: Lantern
B37: Fireplace | D37: Log Lighter
D38: Insert
A40: Duct System Type
B41: Flex | D41: Progressive
B42: Ductboard | D42: Conventional
B43: Metal

Sheet Sheet1
C1: AccountingCode1 | D1: ItemName | E1: ItemDescription | F1: PurchaseUnit | G1: UnitOfMeasure | H1: CoverageRatePurchase | I1: CoverageRateMeasured | J1: FolderLevel1 | K1: FolderLevel2 | L1: FolderLevel3 | M1: FolderLevel4 | N1: FolderLevel5 | O1: CostType1 | P1: UnitCost1 | Q1: ExportId | R1: CostType2 | S1: UnitCost2 | T1: AccountingCode2 | U1: CostType3 | V1: UnitCost3 | W1: AccountingCode3 | X1: CostType4 | Y1: UnitCost4 | Z1: AccountingCode4 | AA1: CostType5 | AB1: UnitCost5 | AC1: AccountingCode5 | AD1: ExternalId
B3: CE0501N05T 5 KW Elec Heater Fused | C3: 81250 | D3: CE0501N05T 5 KW Elec Heater Fused | E3: CE0501N05T 5 KW Elec Heater Fused | F3: each | G3: each | H3: 1 | I3: 1 | J3: Rough Equipment | O3: Material | P3: 51
B4: CE0801N08TS 8 KW Elec Heater Fused | C4: 81260 | D4: CE0801N08TS 8 KW Elec Heater Fused | E4: CE0801N08TS 8 KW Elec Heater Fused | F4: each | G4: each | H4: 1 | I4: 1 | J4: Rough Equipment | O4: Material | P4: 85
B5: CE0901N10T 10 KW Elec Heater Fused | C5: 81270 | D5: CE0901N10T 10 KW Elec Heater Fused | E5: CE0901N10T 10 KW Elec Heater Fused | F5: each | G5: each | H5: 1 | I5: 1 | J5: Rough Equipment | O5: Material | P5: 79
B6: CE3001F15T 15 KW Elec Heater Fused | C6: 81280 | D6: CE3001F15T 15 KW Elec Heater Fused | E6: CE3001F15T 15 KW Elec Heater Fused | F6: each | G6: each | H6: 1 | I6: 1 | J6: Rough Equipment | O6: Material | P6: 147
B7: 58SB0A070E17--12 80 GAS FURNACE | C7: 81430 | D7: 58SB0A070E17--12 80 GAS FURNACE | E7: 58SB0A070E17--12 80 GAS FURNACE | F7: each | G7: each | H7: 1 | I7: 1 | J7: Rough Equipment | O7: Material | P7: 409
B8: 58SB0A090E21--16 80 GAS FURNACE | C8: 81460 | D8: 58SB0A090E21--16 80 GAS FURNACE | E8: 58SB0A090E21--16 80 GAS FURNACE | F8: each | G8: each | H8: 1 | I8: 1 | J8: Rough Equipment | O8: Material | P8: 437
B9: 58SB0A090E21--20 80 GAS FURNACE | C9: 81470 | D9: 58SB0A090E21--20 80 GAS FURNACE | E9: 58SB0A090E21--20 80 GAS FURNACE | F9: each | G9: each | H9: 1 | I9: 1 | J9: Rough Equipment | O9: Material | P9: 461
B10: 59SC2D040E14--10 92 GAS FURNACE | C10: 81600 | D10: 59SC2D040E14--10 92 GAS FURNACE | E10: 59SC2D040E14--10 92 GAS FURNACE | F10: each | G10: each | H10: 1 | I10: 1 | J10: Rough Equipment | O10: Material | P10: 515
B11: 59SC2D040E17--12 92 GAS FURNACE | C11: 81610 | D11: 59SC2D040E17--12 92 GAS FURNACE | E11: 59SC2D040E17--12 92 GAS FURNACE | F11: each | G11: each | H11: 1 | I11: 1 | J11: Rough Equipment | O11: Material | P11: 515
B12: 59SC2D060E14--12 92 GAS FURNACE | C12: 81620 | D12: 59SC2D060E14--12 92 GAS FURNACE | E12: 59SC2D060E14--12 92 GAS FURNACE | F12: each | G12: each | H12: 1 | I12: 1 | J12: Rough Equipment | O12: Material | P12: 528
B13: 59SC2D060E17--14 92 GAS FURNACE | C13: 81630 | D13: 59SC2D060E17--14 92 GAS FURNACE | E13: 59SC2D060E17--14 92 GAS FURNACE | F13: each | G13: each | H13: 1 | I13: 1 | J13: Rough Equipment | O13: Material | P13: 541
B14: 59SC2D080E17--16 92 GAS FURNACE | C14: 81640 | D14: 59SC2D080E17--16 92 GAS FURNACE | E14: 59SC2D080E17--16 92 GAS FURNACE | F14: each | G14: each | H14: 1 | I14: 1 | J14: Rough Equipment | O14: Material | P14: 554
... B212: 11X17X48 DB PLENUM W CAP R8 | C212: 995 | D212: 11X17X48 DB PLENUM W CAP R8 | E212: 11X17X48 DB PLENUM W CAP R8 | F212: each | G212: each | H212: 1 | I212: 1 | J212: Rough Material | O212: Material | P212: 59.87
A213: 10000 | B213: 11-1/4X18X24 DB PLENUM W CAP R8 | C213: 10000 | D213: 11-1/4X18X24 DB PLENUM W CAP R8.. | E213: 11-1/4X18X24 DB PLENUM W CAP R8.. | F213: each | G213: each | H213: 1 | I213: 1 | J213: Rough Material | O213: Material | P213: 31.08
A214: 10005 | B214: 11-1/4X18X24 DB SLEEVE NO CAP R8 | C214: 10005 | D214: 11-1/4X18X24 DB SLEEVE - NO CAP R8 | E214: 11-1/4X18X24 DB SLEEVE - NO CAP R8 | F214: each | G214: each | H214: 1 | I214: 1 | J214: Rough Material | O214: Material | P214: 30
A215: 10010 | B215: 11-1/4X18X48 DB PLENUM W CAP R8 | C215: 10010 | D215: 11-1/4X18X48 DB PLENUM W CAP R8 | E215: 11-1/4X18X48 DB PLENUM W CAP R8 | F215: each | G215: each | H215: 1 | I215: 1 | J215: Rough Material | O215: Material | P215: 62.16
A216: 10020 | B216: 14-1/2X18X24 DB PLENUM W CAP R8 | C216: 10020 | D216: 14-1/2X18X24 DB PLENUM W CAP R8 | E216: 14-1/2X18X24 DB PLENUM W CAP R8 | F216: each | G216: each | H216: 1 | I216: 1 | J216: Rough Material | O216: Material | P216: 33.46
A217: 10025 | B217: 14-1/2X18X48DB SLEEVE NO CAP R8 | C217: 10025 | D217: 14-1/2X18X24 DB SLEEVE - NO CAP R8 | E217: 14-1/2X18X24 DB SLEEVE - NO CAP R8 | F217: each | G217: each | H217: 1 | I217: 1 | J217: Rough Material | O217: Material | P217: 32
A218: 10030 | B218: 14-1/2X18X48 DB PLENUM W CAP R8 | C218: 10030 | D218: 14-1/2X18X48 DB PLENUM W CAP R8 | E218: 14-1/2X18X48 DB PLENUM W CAP R8 | F218: each | G218: each | H218: 1 | I218: 1 | J218: Rough Material | O218: Material | P218: 62.58
A219: 10031 | B219: 14-3/4X17X24 DB PLENUM W CAP R8 | C219: 10031 | D219: 14-3/4X17X24 DB PLENUM W CAP R8 | E219: 14-3/4X17X24 DB PLENUM W CAP R8 | F219: each | G219: each | H219: 1 | I219: 1 | J219: Rough Material | O219: Material | P219: 46.71
A220: 10032 | B220: 14-3/4X17X24 DB SLEEVE - NO CAP R8 | C220: 10032 | D220: 14-3/4X17X24 DB SLEEVE - NO CAP R8 | E220: 14-3/4X17X24 DB SLEEVE - NO CAP R8 | F220: each | G220: each | H220: 1 | I220: 1 | J220: Rough Material | O220: Material | P220: 38.8
A221: 10033 | B221: 14-3/4X17X48 DB PLENUM W CAP R8 | C221: 10033 | D221: 14-3/4X17X48 DB PLENUM W CAP R8 | E221: 14-3/4X17X48 DB PLENUM W CAP R8 | F221: each | G221: each | H221: 1 | I221: 1 | J221: Rough Material | O221: Material | P221: 63.94
A222: 10034 | B222: 17X17X24 DB PLENUM W CAP R8 | C222: 10034 | D222: 17X17X24 DB PLENUM W CAP R8 | E222: 17X17X24 DB PLENUM W CAP R8 | F222: each | G222: each | H222: 1 | I222: 1 | J222: Rough Material | O222: Material | P222: 47.97
A223: 10035 | B223: 17X17X24 DB SLEEVE - NO CAP R8 | C223: 10035 | D223: 17X17X24 DB SLEEVE - NO CAP R8 | E223: 17X17X24 DB SLEEVE - NO CAP R8 | F223: each | G223: each | H223: 1 | I223: 1 | J223: Rough Material | O223: Material | P223: 40.02
A224: 10036 | B224: 17X17X48 DB PLENUM W CAP R8 | C224: 10036 | D224: 17X17X48 DB PLENUM W CAP R8 | E224: 17X17X48 DB PLENUM W CAP R8 | F224: each | G224: each | H224: 1 | I224: 1 | J224: Rough Material | O224: Material | P224: 66.39
... A243: 10120 | B243: 24-1/2 X 12-1/2 X 12 METAL BOX (UNINSUL) | C243: 10120 | D243: 24-1/2 X 12-1/2 X 12 METAL BOX (UNINSUL) | E243: 24-1/2 X 12-1/2 X 12 METAL BOX (UNINSUL) | F243: each | G243: each | H243: 1 | I243: 1 | J243: Rough Material | O243: Material | P243: 18.95
A244: 10130 | B244: 25-1/2 X14-1/2 X 12 METAL BOX (UNINSUL) | C244: 10130 | D244: 25-1/2 X 12-1/2 X 12 METAL BOX (UNINSUL)
A245: 10140 | B245: 12-1/2 X 12-1/2 X 12 METAL BOX R8 | C245: 10140 | D245: 12-1/2 X 12-1/2 X 12 RTN AIR BOX R8 | E245: 12-1/2 X 12-1/2 X 12 RTN AIR BOX R8 | F245: each | G245: each | H245: 1 | I245: 1 | J245: Rough Material | O245: Material | P245: 19.92
A246: 10150 | B246: 14-1/2 X 14-1/2 x 12 METAL BOX R8 | C246: 10150 | D246: 14-1/2 X 14-1/2 X 12 RTN AIR BOX R8 | E246: 14-1/2 X 14-1/2 X 12 RTN AIR BOX R8 | F246: each | G246: each | H246: 1 | I246: 1 | J246: Rough Material | O246: Material | P246: 24.62
A247: 10160 | B247: 16-1/2 X 16-1/2 X 12 METAL BOX R8 | C247: 10160 | D247: 16-1/2 X 16-1/2 X 12 RTN AIR BOX R8 | E247: 16-1/2 X 16-1/2 X 12 RTN AIR BOX R8 | F247: each | G247: each | H247: 1 | I247: 1 | J247: Rough Material | O247: Material | P247: 29.73
B248: 16-1/2 X 25-1/2 X 12 RTN AIR BOX R8 | C248: NS10095 | D248: 16-1/2 X 25-1/2 X 12 RTN AIR BOX R8 | E248: 16-1/2 X 25-1/2 X 123 RTN AIR BOX R8 | F248: each | G248: each | H248: 1 | I248: 1 | J248: Rough Material | O248: Material | P248: 0
A249: 10170 | B249: 20-1/2 X 14-1/2 X 12 METAL BOX R8 | C249: 10170 | D249: 20-1/2 X 14-1/2 X 12 RTN AIR BOX R8 | E249: 20-1/2 X 14-1/2 X 12 RTN AIR BOX R8 | F249: each | G249: each | H249: 1 | I249: 1 | J249: Rough Material | O249: Material | P249: 32.9
A250: 10180 | B250: 20-1/2 X 20-1/2 X 12 METAL BOX R8 | C250: 10180 | D250: 20-1/2 X 20-1/2 X 12 RTN AIR BOX R8 | E250: 20-1/2 X 20-1/2 X 12 RTN AIR BOX R8 | F250: each | G250: each | H250: 1 | I250: 1 | J250: Rough Material | O250: Material | P250: 41.22
A251: 10190 | B251: 24-1/2 X 12-1/2 X 12 METAL BOX R8 | C251: 10190 | D251: 24-1/2 X 12-1/2 X 12 RTN AIR BOX R8 | E251: 24-1/2 X 12-1/2 X 12 RTN AIR BOX R8 | F251: each | G251: each | H251: 1 | I251: 1 | J251: Rough Material | O251: Material | P251: 35.27
A252: 10200 | B252: 25-1/2 X 14-1/2 X 12 R8 METAL BOX R8 | C252: 10200 | D252: 25-1/2 X 14-1/2 X 12 RTN AIR BOX R8 | E252: 25-1/2 X 14-1/2 X 12 RTN AIR BOX R8 | F252: each | G252: each | H252: 1 | I252: 1 | J252: Rough Material | O252: Material | P252: 53.94
A253: 10210 | B253: 25-1/2 X 16-1/2 X 12 METAL BOX R8 | C253: 10210 | D253: 25-1/2 X 16-1/2 X 12 RTN AIR BOX R8 | E253: 25-1/2 X 16-1/2 X 12 RTN AIR BOX R8 | F253: each | G253: each | H253: 1 | I253: 1 | J253: Rough Material | O253: Material | P253: 43.13
A254: 10220 | B254: 25-1/2 X 20-1/2 X 12 METAL BOX R8 | C254: 10220 | D254: 25-1/2 X 20-1/2 X 12 RTN AIR BOX R8 | E254: 25-1/2 X 20-1/2 X 12 RTN AIR BOX R8 | F254: each | G254: each | H254: 1 | I254: 1 | J254: Rough Material | O254: Material | P254: 49.7
A255: 11000 | B255: 14-1/2X24X18 PLATFORM BOX | C255: 11000 | D255: 14-1/2X24X18 PLATFORM BOX | E255: 14-1/2X24X18 PLATFORM BOX | F255: each | G255: each | H255: 1 | I255: 1 | J255: Rough Material | O255: Material | P255: 40.62
A256: 11005 | B256: 14-3/4X22X18 PLATFORM BOX | C256: 11005 | D256: 14-3/4X22X18 PLATFORM BOX | E256: 14-3/4X22X18 PLATFORM BOX | F256: each | G256: each | H256: 1 | I256: 1 | J256: Rough Material | O256: Material | P256: 53.98
A257: 11010 | B257: 17-3/4X24X18 PLATFORM BOX | C257: 11010 | D257: 17-3/4X24X18 PLATFORM BOX | E257: 17-3/4X24X18 PLATFORM BOX | F257: each | G257: each | H257: 1 | I257: 1 | J257: Rough Material | O257: Material | P257: 47.33
A258: 11015 | B258: 18-3/4X22X18 PLATFORM BOX | C258: 11015 | D258: 18-3/4X22X18 PLATFORM BOX | E258: 18-3/4X22X18 PLATFORM BOX | F258: each | G258: each | H258: 1 | I258: 1 | J258: Rough Material | O258: Material | P258: 0
A259: 11020 | B259: 21X24X18 PLATFORM BOX | C259: 11020 | D259: 21X24X18 PLATFORM BOX | E259: 21X24X18 PLATFORM BOX | F259: each | G259: each | H259: 1 | I259: 1 | J259: Rough Material | O259: Material | P259: 54.05
A260: 11022 | B260: 21-1/4X22X18 PLATFORM BOX | C260: 11022 | D260: 21-1/4X22X18 PLATFORM BOX | E260: 21-1/4X22X18 PLATFORM BOX | F260: each | G260: each | H260: 1 | I260: 1 | J260: Rough Material | O260: Material | P260: 66.62
... A269: 11065 | B269: 30X34 24GA DRN PAN NO HOLE | C269: 11065 | D269: 30X34 24GA DRN PAN NO HOLE | E269: 30X34 24GA DRN PAN NO HOLE | F269: each | G269: each | H269: 1 | I269: 1 | J269: Rough Material | O269: Material | P269: 36.38
A270: 11070 | B270: 30X36 24GA DRN PAN
A271: 11080 | B271: 30X60 24GA DRN PAN | C271: 11080 | D271: 30X60 24GA DRN PAN | E271: 30X60 24GA DRN PAN | F271: each | G271: each | H271: 1 | I271: 1 | J271: Rough Material | O271: Material | P271: 48.06
A272: 11090 | B272: 32X70 24GA DRN PAN
A273: 11095 | B273: 34X75 24GA DRN PAN | C273: 11095 | D273: 34X75 24GA DRN PAN | E273: 34X75 24GA DRN PAN | F273: each | G273: each | H273: 1 | I273: 1 | J273: Rough Material | O273: Material | P273: 61.95
A274: 11100 | B274: 36X80 24GA DRN PAN | C274: 11100 | D274: 36X80 24GA DRN PAN | E274: 36X80 24GA DRN PAN | F274: each | G274: each | H274: 1 | I274: 1 | J274: Rough Material | O274: Material | P274: 65.54
A275: 12000 | B275: IX48X120 2" R8 DB 6 SHT cm
A276: 12010 | B276: 48X96 24 GA SHEET METAL
A277: 12020 | B277: 48X96 26 GA SHEET METAL | C277: 12020 | D277: 48X96 26 GA SHEET METAL | E277: 48X96 26 GA SHEET METAL | F277: each | G277: each | H277: 1 | I277: 1 | J277: Rough Material | O277: Material | P277: 41.17
A278: 13320 | B278: 16 GA ANGLE 2X2
A279: 13330 | B279: 100 FT COIL 30 GA GALV HGR STRP
A280: 13340 | B280: 120 26GA S CLEAT | C280: 13340 | D280: 120 26GA S CLEAT | E280: 120 26GA S CLEAT | F280: each | G280: each | H280: 1 | I280: 1 | J280: Rough Material | O280: Material | P280: 5.95
A281: 13350 | B281: 120 26GA DRV CLEAT | C281: 13350 | D281: 120 26GA DRV CLEAT | E281: 120 26GA DRV CLEAT | F281: each | G281: each | H281: 1 | I281: 1 | J281: Rough Material | O281: Material | P281: 3.16
A282: 13355 | B282: 120 28GA DRV CLEAT | C282: 13355 | D282: 120 28GA DRV CLEAT | E282: 120 28GA DRV CLEAT | F282: each | G282: each | H282: 1 | I282: 1 | J282: Rough Material | O282: Material | P282: 3.68
A283: 20140 | B283: 3X48X50 FSK DUCT WRAP R8 | C283: 20140 | D283: 3X48X50 FSK DUCT WRAP R8 | E283: 3X48X50 FSK DUCT WRAP R8 | F283: each | G283: each | H283: 1 | I283: 1 | J283: Rough Material | O283: Material | P283: 34.23
A284: 20150 | B284: 2.2X48X75 FSK DUCT WRAP R6 | C284: NS23000 | D284: INSULATION WRAP 2 1/5X48X75 | E284: INSULATION WRAP 2 1/5X48X75 | F284: each | G284: each | H284: 1 | I284: 1 | J284: Rough Material | O284: Material | P284: 0
A285: 12030 | B285: 10X4X4 STRT BOOT | C285: 12030 | D285: 10X4X4 STRT BOOT | E285: 10X4X4 STRT BOOT | F285: each | G285: each | H285: 1 | I285: 1 | J285: Rough Material | O285: Material | P285: 3.46
A286: 12040 | B286: 10X4X6 STRT BOOT | C286: 12040 | D286: 10X4X6 STRT BOOT | E286: 10X4X6 STRT BOOT | F286: each | G286: each | H286: 1 | I286: 1 | J286: Rough Material | O286: Material | P286: 3.09
A287: 12050 | B287: 12X4X7 STRT BOOT | C287: 12050 | D287: 12X4X7 STRT BOOT | E287: 12X4X7 STRT BOOT | F287: each | G287: each | H287: 1 | I287: 1 | J287: Rough Material | O287: Material | P287: 3.98
A288: 12060 | B288: 14X4X8 STRT BOOT | C288: 12060 | D288: 14X4X8 STRT BOOT | E288: 14X4X8 STRT BOOT | F288: each | G288: each | H288: 1 | I288: 1 | J288: Rough Material | O288: Material | P288: 5.85
A289: 12070 | B289: 14X6X8 STRT BOOT | C289: 12070 | D289: 14X6X8 STRT BOOT | E289: 14X6X8 STRT BOOT | F289: each | G289: each | H289: 1 | I289: 1 | J289: Rough Material | O289: Material | P289: 5.18
A290: 12080 | B290: 14X6X9 STRT BOOT | C290: 12080 | D290: 14X6X9 STRT BOOT | E290: 14X6X9 STRT BOOT | F290: each | G290: each | H290: 1 | I290: 1 | J290: Rough Material | O290: Material | P290: 9.11
A291: 12090 | B291: 10X4X4 90 ANGLE BOOT | C291: 12090 | D291: 10X4X4 90 ANGLE BOOT | E291: 10X4X4 90 ANGLE BOOT | F291: each | G291: each | H291: 1 | I291: 1 | J291: Rough Material | O291: Material | P291: 4.05
A292: 12100 | B292: 10X4X6 90 ANGLE BOOT | C292: 12100 | D292: 10X4X6 90 ANGLE BOOT | E292: 10X4X6 90 ANGLE BOOT | F292: each | G292: each | H292: 1 | I292: 1 | J292: Rough Material | O292: Material | P292: 3.1
A293: 12110 | B293: 12X4X7 90 ANGLE BOOT | C293: 12110 | D293: 12X4X7 90 ANGLE BOOT | E293: 12X4X7 90 ANGLE BOOT | F293: each | G293: each | H293: 1 | I293: 1 | J293: Rough Material | O293: Material | P293: 4.31
A294: 12120 | B294: 14X4X8 90 ANGLE BOOT | C294: 12120 | D294: 14X4X8 90 ANGLE BOOT | E294: 14X4X8 90 ANGLE BOOT | F294: each | G294: each | H294: 1 | I294: 1 | J294: Rough Material | O294: Material | P294: 6.95
A295: 12130 | B295: 14X6X8 90 ANGLE BOOT | C295: 12130 | D295: 14X6X8 90 ANGLE BOOT | E295: 14X6X8 90 ANGLE BOOT | F295: each | G295: each | H295: 1 | I295: 1 | J295: Rough Material | O295: Material | P295: 5.65
A296: 12140 | B296: 14X6X9 90 ANGLE BOOT | C296: 12140 | D296: 14X6X9 90 ANGLE BOOT | E296: 14X6X9 90 ANGLE BOOT | F296: each | G296: each | H296: 1 | I296: 1 | J296: Rough Material | O296: Material | P296: 9.65
... A302: 12200 | B302: 14X6X9 CNTR END BOOT | C302: 12200 | D302: 14X6X9 CNTR END BOOT | E302: 14X6X9 CNTR END BOOT | F302: each | G302: each | H302: 1 | I302: 1 | J302: Rough Material | O302: Material | P302: 7.51
A303: 12201 | B303: 6X14X8 FIRE RATED 90 BOOT | C303: 12201 | D303: 6X14X8 FIRE RATED 90 BOOT | F303: each | G303: each | H303: 1 | I303: 1 | J303: Rough Material | O303: Material | P303: 42
A304: 12202 | B304: 6X12X7 FIRE RATED 90 BOOT | C304: 12202 | D304: 6X12X7 FIRE RATED 90 BOOT | E304: 6X12X7 FIRE RATED 90 BOOT | F304: each | G304: each | H304: 1 | I304: 1 | J304: Rough Material | O304: Material | P304: 36.25
A305: 12203 | B305: 4X10X6 FIRE RATED 90 BOOT | C305: 12203 | D305: 4X10X6 FIRE RATED 90 BOOT | E305: 4X10X6 FIRE RATED 90 BOOT | F305: each | G305: each | H305: 1 | I305: 1 | J305: Rough Material | O305: Material | P305: 0
A306: 12204 | B306: 6X10X6 FIRE RATED 90 BOOT | C306: 12204 | D306: 6X10X6 FIRE RATED 90 BOOT | E306: 6X10X6 FIRE RATED 90 BOOT | F306: each | G306: each | H306: 1 | I306: 1 | J306: Rough Material | O306: Material | P306: 34.35
A307: 12205 | B307: 16X12 RADIATION DAMPER | C307: 12205 | D307: 16X12 RADIATION DAMPER | E307: 16X12 RADIATION DAMPER | F307: each | G307: each | H307: 1 | I307: 1 | J307: Rough Material | O307: Material | P307: 24.25
A308: 12206 | B308: BROAN 80RDH FAN HOUSING w RADIATION DAMPER | C308: 12206 | D308: BROAN 80RDH FAN HOUSING w RADIATION DAMPER | E308: BROAN 80RDH FAN HOUSING w RADIATION DAMPER | F308: each | G308: each | H308: 1 | I308: 1 | J308: Rough Material | O308: Material | P308: 57
A309: 12207 | B309: BROAN 80RDH FAN TRIM (RADIATION DAMPER) | C309: 12207 | D309: BROAN 80RDH FAN TRIM (RADIATION DAMPER) | E309: BROAN 80RDH FAN TRIM (RADIATION DAMPER) | F309: each | G309: each | H309: 1 | I309: 1 | J309: Rough Material | O309: Material | P309: 37.5
A310: 12208 | B310: 16" X 25' FIRE WRAP (DRYER) | C310: 12208 | D310: 16" X 25' FIRE WRAP (DRYER) | E310: 16" X 25' FIRE WRAP (DRYER) | F310: each | G310: each | H310: 1 | I310: 1 | J310: Rough Material | O310: Material | P310: 160
A311: 12210 | B311: 10X4 BOOT FRM 24 | C311: 12210 | D311: 10X4 BOOT FRM 24 | E311: 10X4 BOOT FRM 24 | F311: each | G311: each | H311: 1 | I311: 1 | J311: Rough Material | O311: Material | P311: 3.32
A312: 12245 | B312: 10X6 BOOT FRM 24 | C312: 12245 | D312: 10X6 BOOT FRM 24 | E312: 10X6 BOOT FRM 24 | F312: each | G312: each | H312: 1 | I312: 1 | J312: Rough Material | O312: Material | P312: 4.17
A313: 12220 | B313: 12X4 BOOT FRM 24 | C313: 12220 | D313: 12X4 BOOT FRM 24 | E313: 12X4 BOOT FRM 24 | F313: each | G313: each | H313: 1 | I313: 1 | J313: Rough Material | O313: Material | P313: 3.31
A314: 12246 | B314: 12X6 BOOT FRM 24 | C314: 12246 | D314: 12X6 BOOT FRM 24 | F314: each | G314: each | H314: 1 | I314: 1 | J314: Rough Material | O314: Material | P314: 4.17
A315: 12230 | B315: 14X4 BOOT FRM 24 | C315: 12230 | D315: 14X4 BOOT FRM 24 | E315: 14X4 BOOT FRM 24 | F315: each | G315: each | H315: 1 | I315: 1 | J315: Rough Material | O315: Material | P315: 4.53
A316: 12240 | B316: 14X6 BOOT FRM 24 | C316: 12240 | D316: 14X6 BOOT FRM 24 | E316: 14X6 BOOT FRM 24 | F316: each | G316: each | H316: 1 | I316: 1 | J316: Rough Material | O316: Material | P316: 4.09
A317: 12250 | B317: 26 BOOT RAIL
A318: 12260 | B318: 4 MET START COLLAR | C318: 12260 | D318: 4 MET START COLLAR | E318: 4 MET START COLLAR | F318: each | G318: each | H318: 1 | I318: 1 | J318: Rough Material | O318: Material | P318: 1.16
A319: 12280 | B319: 6 MET START COLLAR | C319: 12280 | D319: 6 MET START COLLAR | E319: 6 MET START COLLAR | F319: each | G319: each | H319: 1 | I319: 1 | J319: Rough Material | O319: Material | P319: 1.3
A320: 12290 | B320: 7 MET START COLLAR | C320: 12290 | D320: 7 MET START COLLAR | E320: 7 MET START COLLAR | F320: each | G320: each | H320: 1 | I320: 1 | J320: Rough Material | O320: Material | P320: 1.56
A321: 12300 | B321: 8 MET START COLLAR | C321: 12300 | D321: 8 MET START COLLAR | E321: 8 MET START COLLAR | F321: each | G321: each | H321: 1 | I321: 1 | J321: Rough Material | O321: Material | P321: 1.75
A322: 12310 | B322: 9 MET START COLLAR | C322: 12310 | D322: 9 MET START COLLAR | E322: 9 MET START COLLAR | F322: each | G322: each | H322: 1 | I322: 1 | J322: Rough Material | O322: Material | P322: 2.18
A323: 12320 | B323: 10 MET START COLLAR | C323: 12320 | D323: 10 MET START COLLAR | E323: 10 MET START COLLAR | F323: each | G323: each | H323: 1 | I323: 1 | J323: Rough Material | O323: Material | P323: 2.19
A324: 12330 | B324: 12 MET START COLLAR | C324: 12330 | D324: 12 MET START COLLAR | E324: 12 MET START COLLAR | F324: each | G324: each | H324: 1 | I324: 1 | J324: Rough Material | O324: Material | P324: 2.89
A325: 12340 | B325: 14 MET START COLLAR | C325: 12340 | D325: 14 MET START COLLAR | E325: 14 MET START COLLAR | F325: each | G325: each | H325: 1 | I325: 1 | J325: Rough Material | O325: Material | P325: 3.57
A326: 12350 | B326: 16 MET START COLLAR | C326: 12350 | D326: 16 MET START COLLAR | E326: 16 MET START COLLAR | F326: each | G326: each | H326: 1 | I326: 1 | J326: Rough Material | O326: Material | P326: 6.2
A327: 12360 | B327: 18 MET START COLL
A328: 12370 | B328: 20 MET START COLL
A329: 12380 | B329: 4 DB START COLLAR | C329: 12380 | D329: 4 DB START COLLAR | E329: 4 DB START COLLAR | F329: each | G329: each | H329: 1 | I329: 1 | J329: Rough Material | O329: Material | P329: 1.21
...

Sheet Sheet9
A1: 17200 | B1: CONDENSATE PUMP PRO CP 225 | C1: 1 | D1: 45.44 | E1: each | F1: =C1*D1 -> 45.44
A2: 17220 | B2: 3/8 x 3/4 Barb x MIP | C2: 1 | D2: 4.2 | E2: each | F2: =C2*D2 -> 4.2
A3: 17610 | B3: 30X34 24GA DRN PAN NO HOLE | C3: 1 | D3: 36.38 | E3: each | F3: =C3*D3 -> 36.38
A4: 17660 | B4: 36X80 24GA DRN PAN | C4: 1 | D4: 65.54 | E4: each | F4: =C4*D4 -> 65.54
A5: 18610 | B5: 120 26GA DRV CLEAT | C5: 2 | D5: 3.16 | E5: each | F5: =C5*D5 -> 6.32
A6: 20000 | B6: 10X4X4 STRT BOOT | C6: 7 | D6: 3.55 | E6: each | F6: =C6*D6 -> 24.85
A7: 20010 | B7: 10X4X6 STRT BOOT | C7: 10 | D7: 3.17 | E7: each | F7: =C7*D7 -> 31.7
A8: 20020 | B8: 12X4X7 STRT BOOT | C8: 6 | D8: 4.04 | E8: each | F8: =C8*D8 -> 24.24
A9: 20060 | B9: 10X4X4 90 ANGLE BOOT | C9: 1 | D9: 4.16 | E9: each | F9: =C9*D9 -> 4.16
A10: 20070 | B10: 10X4X6 90 ANGLE BOOT | C10: 3 | D10: 3.17 | E10: each | F10: =C10*D10 -> 9.51
A11: 20080 | B11: 12X4X7 90 ANGLE BOOT | C11: 2 | D11: 4.43 | E11: each | F11: =C11*D11 -> 8.86
A12: 20090 | B12: 14X4X8 90 ANGLE BOOT | C12: 1 | D12: 7.12 | E12: each | F12: =C12*D12 -> 7.12
... A92: 40095 | B92: 3/8 ID X 50 CLR VINYL TUBE - 738 | C92: 1 | D92: 13.42 | E92: each | F92: =C92*D92 -> 13.42
A93: 17210 | B93: 3/8 x 1/2 Barb x MIP - 701-012D | D93: 3.85 | E93: each | F93: =C93*D93 -> 0
A94: 17230 | B94: 1/2 x 3/4 Barb x MIP - 701-002D | D94: 3.25 | E94: each | F94: =C94*D94 -> 0
A95: 17500 | B95: 32X32X3 PLASTIC EQUIP PAD | D95: 47.93 | E95: each | F95: =C95*D95 -> 0
A96: 17520 | B96: 36X40X3 PLASTIC EQUIP PAD | E96: each | F96: =C96*D96 -> 0
A97: 17600 | B97: 24X34 24GA DRN PAN NO HOLE | D97: 35.75 | E97: each | F97: =C97*D97 -> 0
A98: 17620 | B98: 30X36 24GA DRN PAN | E98: each | F98: =C98*D98 -> 0
A99: 17630 | B99: 30X60 24GA DRN PAN | D99: 48.62 | E99: each | F99: =C99*D99 -> 0
A100: 17640 | B100: 32X70 24GA DRN PAN | E100: each | F100: =C100*D100 -> 0
A101: 17650 | B101: 34X75 24GA DRN PAN | D101: 61.95 | E101: each | F101: =C101*D101 -> 0
A102: 17670 | B102: 12X10X3-1/2 GAS BOX - NO HOLE | D102: 9 | E102: each | F102: =C102*D102 -> 0
A103: 18000 | B103: 11X17X24 DB PLENUM W CAP R8 | D103: 44.68 | E103: each | F103: =C103*D103 -> 0
A104: 18010 | B104: 11X17X24 DB SLEEVE - NO CAP R8 | D104: 36.76 | E104: each | F104: =C104*D104 -> 0
A105: 18020 | B105: 11X17X48 DB PLENUM W CAP R8 | D105: 59.87 | E105: each | F105: =C105*D105 -> 0
A106: 18030 | B106: 11-1/4X18X24 DB PLENUM W CAP R8 | D106: 31.08 | E106: each | F106: =C106*D106 -> 0
A107: 18040 | B107: 11-1/4X18X24 DB SLEEVE NO CAP R8 | D107: 30 | E107: each | F107: =C107*D107 -> 0
A108: 18050 | B108: 11-1/4X18X48 DB PLENUM W CAP R8 | D108: 62.16 | E108: each | F108: =C108*D108 -> 0
A109: 18060 | B109: 14-1/2X18X24 DB PLENUM W CAP R8 | D109: 33.46 | E109: each | F109: =C109*D109 -> 0
A110: 18070 | B110: 14-1/2X18X48DB SLEEVE NO CAP R8 | D110: 32 | E110: each | F110: =C110*D110 -> 0
A111: 18080 | B111: 14-1/2X18X48 DB PLENUM W CAP R8 | D111: 62.58 | E111: each | F111: =C111*D111 -> 0
A112: 18100 | B112: 14-3/4X17X24 DB SLEEVE - NO CAP R8 | D112: 38.8 | E112: each | F112: =C112*D112 -> 0
... A146: 18540 | B146: 4X4 WALL CAP HOOD - LINESET COVER | D146: 7 | E146: each | F146: =C146*D146 -> 0
A147: 18550 | B147: IX48X120 2" R8 DB 6 SHT | E147: each | F147: =C147*D147 -> 0
A148: 18560 | B148: 48X96 24 GA SHEET METAL | E148: each | F148: =C148*D148 -> 0
A149: 18570 | B149: 48X96 26 GA SHEET METAL | D149: 41.17 | E149: each | F149: =C149*D149 -> 0
A150: 18590 | B150: 1/2" x 1-1/2"-48" DRYWALLFRAME | D150: 2.75 | E150: each | F150: =C150*D150 -> 0
A151: 18600 | B151: 120 26GA S CLEAT | D151: 5.95 | E151: each | F151: =C151*D151 -> 0
A152: 18620 | B152: 120 28GA DRV CLEAT | D152: 3.68 | E152: each | F152: =C152*D152 -> 0
A153: 18630 | B153: 3X48X50 FSK DUCT WRAP R8 | D153: 34.23 | E153: each | F153: =C153*D153 -> 0
A154: 18640 | B154: 2.2X48X75 FSK DUCT WRAP R6 | D154: 0 | E154: each | F154: =C154*D154 -> 0
A155: 20030 | B155: 14X4X8 STRT BOOT | D155: 6 | E155: each | F155: =C155*D155 -> 0
A156: 20040 | B156: 14X6X8 STRT BOOT | D156: 5.31 | E156: each | F156: =C156*D156 -> 0
A157: 20050 | B157: 14X6X9 STRT BOOT | D157: 9.4 | E157: each | F157: =C157*D157 -> 0
A158: 20110 | B158: 14X6X9 90 ANGLE BOOT | D158: 9.4 | E158: each | F158: =C158*D158 -> 0
A159: 20170 | B159: 14X6X9 CNTR END BOOT | D159: 7.61 | E159: each | F159: =C159*D159 -> 0
A160: 20190 | B160: 10X6 BOOT FRM 24 | D160: 3.4 | E160: each | F160: =C160*D160 -> 0
... A169: 20320 | B169: 14 MET START COLLAR | D169: 3.57 | E169: each | F169: =C169*D169 -> 0
A170: 20340 | B170: 18 MET START COLL | E170: each | F170: =C170*D170 -> 0
A171: 20350 | B171: 20 MET START COLL | E171: each | F171: =C171*D171 -> 0
A172: 20400 | B172: 9 DB START COLLAR | D172: 2.18 | E172: each | F172: =C172*D172 -> 0
A173: 20430 | B173: 14 DB START COLLAR | D173: 3.61 | E173: each | F173: =C173*D173 -> 0
A174: 20450 | B174: 18 DB START COLLAR | D174: 21.2 | E174: each | F174: =C174*D174 -> 0
A175: 20460 | B175: 20 DB START COLLAR | D175: 0 | E175: each | F175: =C175*D175 -> 0
A176: 20470 | B176: 4 DB COLLAR W/DMPR | E176: each | F176: =C176*D176 -> 0
A177: 20490 | B177: 7 DB COLLAR W/ DMPR | D177: 9.32 | E177: each | F177: =C177*D177 -> 0
A178: 20500 | B178: 8 DB COLLAR W/ DMPR | D178: 10.16 | E178: each | F178: =C178*D178 -> 0
A179: 20510 | B179: 9 DB COLLAR W/ DMPR | D179: 11.94 | E179: each | F179: =C179*D179 -> 0
A180: 20520 | B180: 10 DB COLLAR W/ DMPR | D180: 10.38 | E180: each | F180: =C180*D180 -> 0
A181: 20530 | B181: 4 SADDLE COLLAR | D181: 0 | E181: each | F181: =C181*D181 -> 0
A182: 20540 | B182: 6 SADDLE COLLAR | D182: 0 | E182: each | F182: =C182*D182 -> 0
A183: 20550 | B183: 7 SADDLE COLLAR | D183: 0 | E183: each | F183: =C183*D183 -> 0
A184: 20560 | B184: 8 SADDLE COLLAR | D184: 0 | E184: each | F184: =C184*D184 -> 0
A185: 20570 | B185: 10 SADDLE COLLAR | D185: 0 | E185: each | F185: =C185*D185 -> 0
A186: 20580 | B186: 12 SADDLE COLLAR | D186: 0 | E186: each | F186: =C186*D186 -> 0
A187: 20590 | B187: 6X4X4 26GA WYE | D187: 10.26 | E187: each | F187: =C187*D187 -> 0
A188: 20600 | B188: 6X6X4 26GA WYE | D188: 9.88 | E188: each | F188: =C188*D188 -> 0
... A197: 20710 | B197: 12XI0XI0 26GA WYE | D197: 23.62 | E197: each | F197: =C197*D197 -> 0
A198: 20720 | B198: 14X12X12 26GAWYE | E198: each | F198: =C198*D198 -> 0
A199: 20740 | B199: 6 30GA 90 ELBOW | D199: 2.05 | E199: each | F199: =C199*D199 -> 0
A200: 20750 | B200: 7 30GA 90 ELBOW | D200: 3.27 | E200: each | F200: =C200*D200 -> 0
A201: 20760 | B201: 8 30GA 90 ELBOW | D201: 3.55 | E201: each | F201: =C201*D201 -> 0
A202: 20770 | B202: 9 30GA 90 ELBOW | D202: 5.75 | E202: each | F202: =C202*D202 -> 0
A203: 20790 | B203: 12 28GA 90 ELBOW | D203: 7.7 | E203: each | F203: =C203*D203 -> 0
A204: 20800 | B204: 14 28GA 90 ELBOW | D204: 10.29 | E204: each | F204: =C204*D204 -> 0
A205: 20810 | B205: 16 26GA 90 ELBOW | D205: 14.56 | E205: each | F205: =C205*D205 -> 0
A206: 20820 | B206: 18 26GA ADJ 90 ELL | D206: 22.97 | E206: each | F206: =C206*D206 -> 0
A207: 20830 | B207: 20 26GA ADJ 90 ELL | D207: 65.1 | E207: each | F207: =C207*D207 -> 0
A208: 20840 | B208: 4 30GA FLEX DUCT CONN | D208: 1.64 | E208: each | F208: =C208*D208 -> 0
A209: 20880 | B209: 9 30GA FLEX DUCT CONN | D209: 1.68 | E209: each | F209: =C209*D209 -> 0
A210: 20910 | B210: 14 30GA FLEX DUCT CONN | D210: 5.16 | E210: each | F210: =C210*D210 -> 0
A211: 20920 | B211: 16 30GA FLEX DUCT CONN | D211: 8.84 | E211: each | F211: =C211*D211 -> 0
A212: 20930 | B212: 18 30GA FLEX DUCT CONN | E212: each | F212: =C212*D212 -> 0
A213: 20940 | B213: 20 30GA FLEX DUCT CONN | E213: each | F213: =C213*D213 -> 0
A214: 20950 | B214: 4 ADHESIVE SADDLE TAKEOFF | E214: each | F214: =C214*D214 -> 0
A215: 20960 | B215: 6 ADHESIVE SADDLE TAKEOFF | D215: 4.75 | E215: each | F215: =C215*D215 -> 0
A216: 20970 | B216: 7 ADHESIVE SADDLE TAKEOFF | D216: 5.45 | E216: each | F216: =C216*D216 -> 0
A217: 20980 | B217: 8 ADHESIVE SADDLE TAKEOFF | D217: 5.56 | E217: each | F217: =C217*D217 -> 0
A218: 20990 | B218: 9 ADHESIVE SADDLE TAKEOFF | E218: each | F218: =C218*D218 -> 0
A219: 21000 | B219: 10 ADHESIVE SADDLE TAKEOFF | D219: 8.9 | E219: each | F219: =C219*D219 -> 0
A220: 21010 | B220: 4 ADHESIVE SADDLE TAKEOFF W DAMPER | D220: 9.51 | E220: each | F220: =C220*D220 -> 0
A221: 21020 | B221: 6 ADHESIVE SADDLE TAKEOFF W DAMPER | D221: 7.91 | E221: each | F221: =C221*D221 -> 0
A222: 21030 | B222: 7 ADHESIVE SADDLE TAKEOFF W DAMPER | D222: 10.84 | E222: each | F222: =C222*D222 -> 0
A223: 21040 | B223: 8 ADHESIVE SADDLE TAKEOFF W DAMPER | D223: 11.27 | E223: each | F223: =C223*D223 -> 0
A224: 21050 | B224: 4X3 26GA RED NO CRMP | D224: 4.17 | E224: each | F224: =C224*D224 -> 0
A225: 21060 | B225: 5X4 26GA REDUCER | D225: 5.17 | E225: each | F225: =C225*D225 -> 0
A226: 21070 | B226: 6X4 26GA TPRD RED | D226: 4.74 | E226: each | F226: =C226*D226 -> 0
A227: 21080 | B227: 6X5 26GA TPRD RED | D227: 4.74 | E227: each | F227: =C227*D227 -> 0
A228: 21090 | B228: 7X4 26GA TPRD RED | E228: each | F228: =C228*D228 -> 0
...
